{"id-58898":{"title":"Consultant","id":58898,"publish-date":1643644121,"featured-image-url":"https:\/\/websitedemos.net\/wp-content\/uploads\/2022\/01\/consultant-04-home.jpg","thumbnail-image-url":"https:\/\/websitedemos.net\/wp-content\/uploads\/2022\/01\/consultant-04-home.jpg","fullpage-thumbnail-image-url":"https:\/\/websitedemos.net\/wp-content\/uploads\/2022\/01\/consultant-04-home.jpg","astra-site-url":"\/\/websitedemos.net\/consultant-04","astra-site-parent-id":2523,"astra-sites-tag":{"2524":"adviser","2527":"authority","2287":"consultancy-services","1621":"consultant","1876":"counsellor","3416":"elementor","2528":"expert-advice","2525":"guide","1880":"mentor","1844":"premium","2526":"specialist"},"astra-sites-type":"agency-mini","astra-site-category":{"27":"business"},"astra-sites-template-category":{"2794":"consulting","2831":"service"},"astra-site-page-builder":"elementor","categories":{"3427":"default","2483":"expert-services","3429":"premium"},"required-plugins":[{"slug":"elementor","init":"elementor\/elementor.php","name":"Elementor"},{"slug":"sureforms","init":"sureforms\/sureforms.php","name":"SureForms"}],"post-status":"publish","post-content":"<!-- wp:paragraph -->\n<p>The Consultant web template is an extended portfolio design with an attractive home page and extra pages to help tell your story. Created to be warm and welcoming, while also modern and professional, this is a very well balanced design.<\/p>\n<!-- \/wp:paragraph -->\n\n<!-- wp:paragraph -->\n<p>The template uses a strong main color with well-chosen complementing colors along with plenty of white space to let you breathe. All while portraying the professionalism you want to communicate on your website.<\/p>\n<!-- \/wp:paragraph -->\n\n<!-- wp:heading -->\n<h2>Key features of the Consultant template<\/h2>\n<!-- \/wp:heading -->\n\n<!-- wp:list -->\n<ul><li>Uses strong colors balanced by lots of white space<\/li><li>Attractive imagery and fonts<\/li><li>Includes subtle animations to help bring the page to life<\/li><li>Has extra pages to outline your products and services<\/li><li>Effective call to action banner ready to go<\/li><li>Compatible with drag and drop page builders<\/li><\/ul>\n<!-- \/wp:list -->","post-excerpt":"Combination business site and portfolio design that\u2019s ideal for all types of consultant","pages":{"id-58901":{"title":"Home","featured-image-url":"https:\/\/websitedemos.net\/wp-content\/uploads\/2022\/01\/consultant-04-home.jpg","thumbnail-image-url":"https:\/\/websitedemos.net\/wp-content\/uploads\/2022\/01\/consultant-04-home.jpg","astra-page-api-url":"https:\/\/websitedemos.net\/consultant-04\/wp-json\/wp\/v2\/pages\/6","dynamic-page":"no","astra-page-url":"\/\/websitedemos.net\/consultant-04\/","astra-sites-tag":{"423":"home"},"site-pages-type":"agency-mini","site-pages-page-builder":"elementor","site-pages-category":[],"site-pages-parent-category":{"60":"business"},"required-plugins":[{"slug":"elementor","init":"elementor\/elementor.php","name":"Elementor"}],"spectra-ver":[]},"id-58899":{"title":"About","featured-image-url":"https:\/\/websitedemos.net\/wp-content\/uploads\/2022\/01\/consultant-04-about.jpg","thumbnail-image-url":"https:\/\/websitedemos.net\/wp-content\/uploads\/2022\/01\/consultant-04-about.jpg","astra-page-api-url":"https:\/\/websitedemos.net\/consultant-04\/wp-json\/wp\/v2\/pages\/9","dynamic-page":"no","astra-page-url":"\/\/websitedemos.net\/consultant-04\/about\/","astra-sites-tag":{"352":"about"},"site-pages-type":"agency-mini","site-pages-page-builder":"elementor","site-pages-category":[],"site-pages-parent-category":{"60":"business"},"required-plugins":[{"slug":"elementor","init":"elementor\/elementor.php","name":"Elementor"}],"spectra-ver":[]},"id-58902":{"title":"Services","featured-image-url":"https:\/\/websitedemos.net\/wp-content\/uploads\/2022\/01\/consultant-04-services.jpg","thumbnail-image-url":"https:\/\/websitedemos.net\/wp-content\/uploads\/2022\/01\/consultant-04-services.jpg","astra-page-api-url":"https:\/\/websitedemos.net\/consultant-04\/wp-json\/wp\/v2\/pages\/12","dynamic-page":"no","astra-page-url":"\/\/websitedemos.net\/consultant-04\/services\/","astra-sites-tag":{"425":"services"},"site-pages-type":"agency-mini","site-pages-page-builder":"elementor","site-pages-category":[],"site-pages-parent-category":{"60":"business"},"required-plugins":[{"slug":"elementor","init":"elementor\/elementor.php","name":"Elementor"}],"spectra-ver":[]},"id-58903":{"title":"Testimonials","featured-image-url":"https:\/\/websitedemos.net\/wp-content\/uploads\/2022\/01\/consultant-04-testimonials.jpg","thumbnail-image-url":"https:\/\/websitedemos.net\/wp-content\/uploads\/2022\/01\/consultant-04-testimonials.jpg","astra-page-api-url":"https:\/\/websitedemos.net\/consultant-04\/wp-json\/wp\/v2\/pages\/14","dynamic-page":"no","astra-page-url":"\/\/websitedemos.net\/consultant-04\/testimonials\/","astra-sites-tag":{"2302":"testimonial"},"site-pages-type":"agency-mini","site-pages-page-builder":"elementor","site-pages-category":[],"site-pages-parent-category":{"60":"business"},"required-plugins":[{"slug":"elementor","init":"elementor\/elementor.php","name":"Elementor"}],"spectra-ver":[]},"id-58900":{"title":"Contact","featured-image-url":"https:\/\/websitedemos.net\/wp-content\/uploads\/2022\/01\/consultant-04-contact.jpg","thumbnail-image-url":"https:\/\/websitedemos.net\/wp-content\/uploads\/2022\/01\/consultant-04-contact.jpg","astra-page-api-url":"https:\/\/websitedemos.net\/consultant-04\/wp-json\/wp\/v2\/pages\/16","dynamic-page":"no","astra-page-url":"\/\/websitedemos.net\/consultant-04\/contact\/","astra-sites-tag":{"415":"contact"},"site-pages-type":"agency-mini","site-pages-page-builder":"elementor","site-pages-category":[],"site-pages-parent-category":{"60":"business"},"required-plugins":[{"slug":"elementor","init":"elementor\/elementor.php","name":"Elementor"},{"slug":"sureforms","init":"sureforms\/sureforms.php","name":"SureForms"}],"spectra-ver":[]}},"spectra-ver":[],"query_args":{"post_type":"astra-sites","post_status":["publish"],"fields":"ids","no_found_rows":true,"paged":29,"posts_per_page":15,"tax_query":{"relation":"AND","0":{"relation":"OR","0":{"taxonomy":"spectra-blocks-ver","field":"slug","terms":["v2","v3"],"operator":"IN"},"1":{"taxonomy":"spectra-blocks-ver","operator":"NOT EXISTS"}},"1":{"taxonomy":"astra-sites-type","field":"slug","terms":["siteground"],"operator":"NOT IN"}},"orderby":"menu_order","order":"ASC"},"related-bb-template":"","related-elementor-template":58898,"related-gutenberg-template":86491,"related_ecommerce_template":0,"ecommerce_parent_template":""},"id-86341":{"title":"Christmas Party","id":86341,"publish-date":1708706637,"featured-image-url":"https:\/\/websitedemos.net\/wp-content\/uploads\/2024\/02\/christmass-party-07.jpg","thumbnail-image-url":"https:\/\/websitedemos.net\/wp-content\/uploads\/2024\/02\/christmass-party-07-600x2427.jpg","fullpage-thumbnail-image-url":"https:\/\/websitedemos.net\/wp-content\/uploads\/2024\/02\/christmass-party-07-400x1618.jpg","astra-site-url":"\/\/websitedemos.net\/christmas-party-07","astra-site-parent-id":3491,"astra-sites-tag":{"3021":"christmas","3029":"christmascheer","3024":"christmasfun","3025":"christmasmood","3022":"christmasparty","3032":"christmaspartyhopping","3026":"christmasspirit","3023":"christmastime","3030":"christmasvibes","3028":"chrstmasparty","3027":"dance","406":"dj","882":"drinks","3031":"holidayparty","407":"music"},"astra-sites-type":"agency-mini","astra-site-category":{"27":"business"},"astra-sites-template-category":{"2869":"dj","2784":"event","2781":"music","2868":"musician-singer"},"astra-site-page-builder":"gutenberg","categories":{"3430":"dark","2489":"event-invitation"},"required-plugins":[{"slug":"ultimate-addons-for-gutenberg","init":"ultimate-addons-for-gutenberg\/ultimate-addons-for-gutenberg.php","name":"Spectra"},{"slug":"sureforms","init":"sureforms\/sureforms.php","name":"SureForms"}],"post-status":"publish","post-content":"","post-excerpt":"","pages":{"id-86343":{"title":"Home","featured-image-url":"https:\/\/websitedemos.net\/wp-content\/uploads\/2024\/02\/christmass-party-07.jpg","thumbnail-image-url":"https:\/\/websitedemos.net\/wp-content\/uploads\/2024\/02\/christmass-party-07-600x2427.jpg","astra-page-api-url":"https:\/\/websitedemos.net\/christmas-party-07\/wp-json\/wp\/v2\/pages\/2106","dynamic-page":"no","astra-page-url":"\/\/websitedemos.net\/christmas-party-07\/","astra-sites-tag":{"423":"home"},"site-pages-type":"agency-mini","site-pages-page-builder":"gutenberg","site-pages-category":[],"site-pages-parent-category":{"60":"business"},"required-plugins":[{"slug":"ultimate-addons-for-gutenberg","init":"ultimate-addons-for-gutenberg\/ultimate-addons-for-gutenberg.php","name":"Spectra"},{"slug":"sureforms","init":"sureforms\/sureforms.php","name":"SureForms"}],"spectra-ver":[]},"id-86345":{"title":"Tickets","featured-image-url":"https:\/\/websitedemos.net\/wp-content\/uploads\/2024\/02\/christmass-party-07-ticket.jpg","thumbnail-image-url":"https:\/\/websitedemos.net\/wp-content\/uploads\/2024\/02\/christmass-party-07-ticket-600x1059.jpg","astra-page-api-url":"https:\/\/websitedemos.net\/christmas-party-07\/wp-json\/wp\/v2\/pages\/2107","dynamic-page":"no","astra-page-url":"\/\/websitedemos.net\/christmas-party-07\/tickets\/","astra-sites-tag":{"2954":"tickets"},"site-pages-type":"agency-mini","site-pages-page-builder":"gutenberg","site-pages-category":[],"site-pages-parent-category":{"60":"business"},"required-plugins":[{"slug":"ultimate-addons-for-gutenberg","init":"ultimate-addons-for-gutenberg\/ultimate-addons-for-gutenberg.php","name":"Spectra"},{"slug":"sureforms","init":"sureforms\/sureforms.php","name":"SureForms"}],"spectra-ver":[]},"id-86344":{"title":"Program","featured-image-url":"https:\/\/websitedemos.net\/wp-content\/uploads\/2024\/02\/christmass-party-07-program.jpg","thumbnail-image-url":"https:\/\/websitedemos.net\/wp-content\/uploads\/2024\/02\/christmass-party-07-program-600x1745.jpg","astra-page-api-url":"https:\/\/websitedemos.net\/christmas-party-07\/wp-json\/wp\/v2\/pages\/2108","dynamic-page":"no","astra-page-url":"\/\/websitedemos.net\/christmas-party-07\/program\/","astra-sites-tag":{"2684":"program"},"site-pages-type":"agency-mini","site-pages-page-builder":"gutenberg","site-pages-category":[],"site-pages-parent-category":{"60":"business"},"required-plugins":[{"slug":"ultimate-addons-for-gutenberg","init":"ultimate-addons-for-gutenberg\/ultimate-addons-for-gutenberg.php","name":"Spectra"},{"slug":"sureforms","init":"sureforms\/sureforms.php","name":"SureForms"}],"spectra-ver":[]},"id-86342":{"title":"Contact","featured-image-url":"https:\/\/websitedemos.net\/wp-content\/uploads\/2024\/02\/christmass-party-07-contact.jpg","thumbnail-image-url":"https:\/\/websitedemos.net\/wp-content\/uploads\/2024\/02\/christmass-party-07-contact-600x728.jpg","astra-page-api-url":"https:\/\/websitedemos.net\/christmas-party-07\/wp-json\/wp\/v2\/pages\/2109","dynamic-page":"no","astra-page-url":"\/\/websitedemos.net\/christmas-party-07\/contact\/","astra-sites-tag":{"415":"contact"},"site-pages-type":"agency-mini","site-pages-page-builder":"gutenberg","site-pages-category":[],"site-pages-parent-category":{"60":"business"},"required-plugins":[{"slug":"ultimate-addons-for-gutenberg","init":"ultimate-addons-for-gutenberg\/ultimate-addons-for-gutenberg.php","name":"Spectra"},{"slug":"sureforms","init":"sureforms\/sureforms.php","name":"SureForms"}],"spectra-ver":[]}},"spectra-ver":[],"query_args":{"post_type":"astra-sites","post_status":["publish"],"fields":"ids","no_found_rows":true,"paged":29,"posts_per_page":15,"tax_query":{"relation":"AND","0":{"relation":"OR","0":{"taxonomy":"spectra-blocks-ver","field":"slug","terms":["v2","v3"],"operator":"IN"},"1":{"taxonomy":"spectra-blocks-ver","operator":"NOT EXISTS"}},"1":{"taxonomy":"astra-sites-type","field":"slug","terms":["siteground"],"operator":"NOT IN"}},"orderby":"menu_order","order":"ASC"},"related-bb-template":"","related-elementor-template":"","related-gutenberg-template":"","related_ecommerce_template":0,"ecommerce_parent_template":""},"id-58981":{"title":"Covid 19 Prevention","id":58981,"publish-date":1643644731,"featured-image-url":"https:\/\/websitedemos.net\/wp-content\/uploads\/2022\/01\/covid-prevention-02-home1.jpg","thumbnail-image-url":"https:\/\/websitedemos.net\/wp-content\/uploads\/2022\/01\/covid-prevention-02-home1.jpg","fullpage-thumbnail-image-url":"https:\/\/websitedemos.net\/wp-content\/uploads\/2022\/01\/covid-prevention-02-home1.jpg","astra-site-url":"\/\/websitedemos.net\/covid-prevention-02","astra-site-parent-id":2550,"astra-sites-tag":{"2556":"avoidance","2554":"covid","2555":"covid-prevention","2558":"disease-prevention","3416":"elementor","2557":"prohibition"},"astra-sites-type":"free","astra-site-category":{"27":"business","39":"free"},"astra-sites-template-category":{"2794":"consulting","2867":"doctor","2834":"healthcare"},"astra-site-page-builder":"elementor","categories":{"3427":"default","3428":"free","2490":"healthcare"},"required-plugins":[{"slug":"elementor","init":"elementor\/elementor.php","name":"Elementor"},{"slug":"header-footer-elementor","init":"header-footer-elementor\/header-footer-elementor.php","name":"Ultimate Addons for Elementor (UAE)"},{"slug":"sureforms","init":"sureforms\/sureforms.php","name":"SureForms"}],"post-status":"publish","post-content":"<!-- wp:paragraph -->\n<p>The Covid 19 Prevention template tries to balance the seriousness of the subject with light hearted design and colors. The use of lots of white space and bright blue and green offsets the emotive nature of the niche.<\/p>\n<!-- \/wp:paragraph -->\n\n<!-- wp:paragraph -->\n<p>The design would suit many areas of care or medicine and can be fully personalized using a page builder. The template works well as it is, with lots of customization options throughout.<\/p>\n<!-- \/wp:paragraph -->\n\n<!-- wp:heading {\"UAGDay\":[]} -->\n<h2 class=\"wp-block-heading\">Key features of the Covid 19 Prevention template<\/h2>\n<!-- \/wp:heading -->\n\n<!-- wp:list -->\n<ul><!-- wp:list-item -->\n<li>Excellent balance of colors and white space<\/li>\n<!-- \/wp:list-item -->\n\n<!-- wp:list-item -->\n<li>Lots of content areas to tell a story<\/li>\n<!-- \/wp:list-item -->\n\n<!-- wp:list-item -->\n<li>Could easily be tweaked to suit any medical niche<\/li>\n<!-- \/wp:list-item -->\n\n<!-- wp:list-item -->\n<li>Includes extra content pages for convenience<\/li>\n<!-- \/wp:list-item -->\n\n<!-- wp:list-item -->\n<li>Attractive contact page with built-in map<\/li>\n<!-- \/wp:list-item -->\n\n<!-- wp:list-item -->\n<li>Compatible with leading drag and drop page builders<\/li>\n<!-- \/wp:list-item --><\/ul>\n<!-- \/wp:list -->","post-excerpt":"Contemporary web design that gives a warm welcome that sets you immediately at ease","pages":{"id-58984":{"title":"Home","featured-image-url":"https:\/\/websitedemos.net\/wp-content\/uploads\/2022\/01\/covid-prevention-02-home1.jpg","thumbnail-image-url":"https:\/\/websitedemos.net\/wp-content\/uploads\/2022\/01\/covid-prevention-02-home1.jpg","astra-page-api-url":"https:\/\/websitedemos.net\/covid-prevention-02\/wp-json\/wp\/v2\/pages\/15","dynamic-page":"no","astra-page-url":"\/\/websitedemos.net\/covid-prevention-02\/","astra-sites-tag":{"423":"home"},"site-pages-type":"free","site-pages-page-builder":"elementor","site-pages-category":[],"site-pages-parent-category":{"60":"business","61":"free"},"required-plugins":[{"slug":"elementor","init":"elementor\/elementor.php","name":"Elementor"},{"slug":"header-footer-elementor","init":"header-footer-elementor\/header-footer-elementor.php","name":"Ultimate Addons for Elementor (UAE)"}],"spectra-ver":[]},"id-58983":{"title":"Contagion","featured-image-url":"https:\/\/websitedemos.net\/wp-content\/uploads\/2022\/01\/covid-prevention-02-contagion-1.jpg","thumbnail-image-url":"https:\/\/websitedemos.net\/wp-content\/uploads\/2022\/01\/covid-prevention-02-contagion-1.jpg","astra-page-api-url":"https:\/\/websitedemos.net\/covid-prevention-02\/wp-json\/wp\/v2\/pages\/442","dynamic-page":"no","astra-page-url":"\/\/websitedemos.net\/covid-prevention-02\/contagion\/","astra-sites-tag":{"2551":"contagion"},"site-pages-type":"free","site-pages-page-builder":"elementor","site-pages-category":[],"site-pages-parent-category":{"60":"business","61":"free"},"required-plugins":[{"slug":"elementor","init":"elementor\/elementor.php","name":"Elementor"},{"slug":"header-footer-elementor","init":"header-footer-elementor\/header-footer-elementor.php","name":"Ultimate Addons for Elementor (UAE)"}],"spectra-ver":[]},"id-58986":{"title":"Symptoms","featured-image-url":"https:\/\/websitedemos.net\/wp-content\/uploads\/2022\/01\/covid-prevention-02-symptoms-1.jpg","thumbnail-image-url":"https:\/\/websitedemos.net\/wp-content\/uploads\/2022\/01\/covid-prevention-02-symptoms-1.jpg","astra-page-api-url":"https:\/\/websitedemos.net\/covid-prevention-02\/wp-json\/wp\/v2\/pages\/558","dynamic-page":"no","astra-page-url":"\/\/websitedemos.net\/covid-prevention-02\/symptoms\/","astra-sites-tag":{"2553":"symptoms"},"site-pages-type":"free","site-pages-page-builder":"elementor","site-pages-category":[],"site-pages-parent-category":{"60":"business","61":"free"},"required-plugins":[{"slug":"elementor","init":"elementor\/elementor.php","name":"Elementor"},{"slug":"header-footer-elementor","init":"header-footer-elementor\/header-footer-elementor.php","name":"Ultimate Addons for Elementor (UAE)"}],"spectra-ver":[]},"id-58985":{"title":"Prevention","featured-image-url":"https:\/\/websitedemos.net\/wp-content\/uploads\/2022\/01\/covid-prevention-02-prevention-1.jpg","thumbnail-image-url":"https:\/\/websitedemos.net\/wp-content\/uploads\/2022\/01\/covid-prevention-02-prevention-1.jpg","astra-page-api-url":"https:\/\/websitedemos.net\/covid-prevention-02\/wp-json\/wp\/v2\/pages\/717","dynamic-page":"no","astra-page-url":"\/\/websitedemos.net\/covid-prevention-02\/prevention\/","astra-sites-tag":{"2552":"prevention"},"site-pages-type":"free","site-pages-page-builder":"elementor","site-pages-category":[],"site-pages-parent-category":{"60":"business","61":"free"},"required-plugins":[{"slug":"elementor","init":"elementor\/elementor.php","name":"Elementor"},{"slug":"header-footer-elementor","init":"header-footer-elementor\/header-footer-elementor.php","name":"Ultimate Addons for Elementor (UAE)"}],"spectra-ver":[]},"id-58982":{"title":"Contact Us","featured-image-url":"https:\/\/websitedemos.net\/wp-content\/uploads\/2022\/01\/covid-prevention-02-contact-us-1.jpg","thumbnail-image-url":"https:\/\/websitedemos.net\/wp-content\/uploads\/2022\/01\/covid-prevention-02-contact-us-1.jpg","astra-page-api-url":"https:\/\/websitedemos.net\/covid-prevention-02\/wp-json\/wp\/v2\/pages\/919","dynamic-page":"no","astra-page-url":"\/\/websitedemos.net\/covid-prevention-02\/contact-us\/","astra-sites-tag":{"454":"contact-us"},"site-pages-type":"free","site-pages-page-builder":"elementor","site-pages-category":[],"site-pages-parent-category":{"60":"business","61":"free"},"required-plugins":[{"slug":"elementor","init":"elementor\/elementor.php","name":"Elementor"},{"slug":"sureforms","init":"sureforms\/sureforms.php","name":"SureForms"},{"slug":"header-footer-elementor","init":"header-footer-elementor\/header-footer-elementor.php","name":"Ultimate Addons for Elementor (UAE)"}],"spectra-ver":[]}},"spectra-ver":[],"query_args":{"post_type":"astra-sites","post_status":["publish"],"fields":"ids","no_found_rows":true,"paged":29,"posts_per_page":15,"tax_query":{"relation":"AND","0":{"relation":"OR","0":{"taxonomy":"spectra-blocks-ver","field":"slug","terms":["v2","v3"],"operator":"IN"},"1":{"taxonomy":"spectra-blocks-ver","operator":"NOT EXISTS"}},"1":{"taxonomy":"astra-sites-type","field":"slug","terms":["siteground"],"operator":"NOT IN"}},"orderby":"menu_order","order":"ASC"},"related-bb-template":"","related-elementor-template":58981,"related-gutenberg-template":59741,"related_ecommerce_template":0,"ecommerce_parent_template":""},"id-47984":{"title":"LearnDash Academy","id":47984,"publish-date":1603828903,"featured-image-url":"https:\/\/websitedemos.net\/wp-content\/uploads\/2020\/10\/learndash-academy-08.jpg","thumbnail-image-url":"https:\/\/websitedemos.net\/wp-content\/uploads\/2020\/10\/learndash-academy-08-600x1847.jpg","fullpage-thumbnail-image-url":"https:\/\/websitedemos.net\/wp-content\/uploads\/2020\/10\/learndash-academy-08-400x1231.jpg","astra-site-url":"\/\/websitedemos.net\/learndash-academy-08","astra-site-parent-id":1691,"astra-sites-tag":{"462":"courses","468":"elearning","467":"learndash","460":"learning","466":"online-courses"},"astra-sites-type":"free","astra-site-category":{"27":"business","39":"free"},"astra-sites-template-category":[],"astra-site-page-builder":"gutenberg","categories":{"2494":"elearning"},"required-plugins":[{"slug":"ultimate-addons-for-gutenberg","init":"ultimate-addons-for-gutenberg\/ultimate-addons-for-gutenberg.php","name":"Spectra"},{"slug":"sfwd-lms","init":"sfwd-lms\/sfwd_lms.php","name":"LearnDash LMS"},{"slug":"learndash-course-grid","init":"learndash-course-grid\/learndash_course_grid.php","name":"LearnDash LMS - Course Grid"},{"slug":"presto-player","init":"presto-player\/presto-player.php","name":"Presto Player"},{"slug":"sureforms","init":"sureforms\/sureforms.php","name":"SureForms"}],"post-status":"publish","post-content":"","post-excerpt":"","pages":{"id-47988":{"title":"Home","featured-image-url":"https:\/\/websitedemos.net\/wp-content\/uploads\/2020\/10\/learndash-academy-08.jpg","thumbnail-image-url":"https:\/\/websitedemos.net\/wp-content\/uploads\/2020\/10\/learndash-academy-08-600x1847.jpg","astra-page-api-url":"https:\/\/websitedemos.net\/learndash-academy-08\/wp-json\/wp\/v2\/pages\/25407","dynamic-page":"yes","astra-page-url":"\/\/websitedemos.net\/learndash-academy-08\/","astra-sites-tag":{"423":"home","814":"homepage"},"site-pages-type":"free","site-pages-page-builder":"gutenberg","site-pages-category":[],"site-pages-parent-category":{"60":"business","61":"free"},"required-plugins":[{"slug":"sfwd-lms","init":"sfwd-lms\/sfwd_lms.php","name":"LearnDash LMS"},{"slug":"learndash-course-grid","init":"learndash-course-grid\/learndash_course_grid.php","name":"LearnDash LMS - Course Grid"},{"slug":"presto-player","init":"presto-player\/presto-player.php","name":"Presto Player"},{"slug":"ultimate-addons-for-gutenberg","init":"ultimate-addons-for-gutenberg\/ultimate-addons-for-gutenberg.php","name":"Spectra"}],"spectra-ver":[]},"id-47986":{"title":"All Courses","featured-image-url":"https:\/\/websitedemos.net\/wp-content\/uploads\/2020\/10\/learndash-academy-08-all-courses.jpg","thumbnail-image-url":"https:\/\/websitedemos.net\/wp-content\/uploads\/2020\/10\/learndash-academy-08-all-courses-600x966.jpg","astra-page-api-url":"https:\/\/websitedemos.net\/learndash-academy-08\/wp-json\/wp\/v2\/pages\/25403","dynamic-page":"yes","astra-page-url":"\/\/websitedemos.net\/learndash-academy-08\/all-courses\/","astra-sites-tag":{"1692":"all-courses","462":"courses"},"site-pages-type":"free","site-pages-page-builder":"gutenberg","site-pages-category":[],"site-pages-parent-category":{"60":"business","61":"free"},"required-plugins":[{"slug":"sfwd-lms","init":"sfwd-lms\/sfwd_lms.php","name":"LearnDash LMS"},{"slug":"learndash-course-grid","init":"learndash-course-grid\/learndash_course_grid.php","name":"LearnDash LMS - Course Grid"},{"slug":"ultimate-addons-for-gutenberg","init":"ultimate-addons-for-gutenberg\/ultimate-addons-for-gutenberg.php","name":"Spectra"}],"spectra-ver":[]},"id-47985":{"title":"About","featured-image-url":"https:\/\/websitedemos.net\/wp-content\/uploads\/2020\/10\/learndash-academy-08-about-2.jpg","thumbnail-image-url":"https:\/\/websitedemos.net\/wp-content\/uploads\/2020\/10\/learndash-academy-08-about-2-600x1582.jpg","astra-page-api-url":"https:\/\/websitedemos.net\/learndash-academy-08\/wp-json\/wp\/v2\/pages\/25401","dynamic-page":"no","astra-page-url":"\/\/websitedemos.net\/learndash-academy-08\/about\/","astra-sites-tag":{"352":"about","455":"about-us"},"site-pages-type":"free","site-pages-page-builder":"gutenberg","site-pages-category":[],"site-pages-parent-category":{"60":"business","61":"free"},"required-plugins":[{"slug":"ultimate-addons-for-gutenberg","init":"ultimate-addons-for-gutenberg\/ultimate-addons-for-gutenberg.php","name":"Spectra"}],"spectra-ver":[]},"id-47987":{"title":"Contact","featured-image-url":"https:\/\/websitedemos.net\/wp-content\/uploads\/2020\/10\/learndash-academy-08-contact-2.jpg","thumbnail-image-url":"https:\/\/websitedemos.net\/wp-content\/uploads\/2020\/10\/learndash-academy-08-contact-2-600x1274.jpg","astra-page-api-url":"https:\/\/websitedemos.net\/learndash-academy-08\/wp-json\/wp\/v2\/pages\/25405","dynamic-page":"no","astra-page-url":"\/\/websitedemos.net\/learndash-academy-08\/contact\/","astra-sites-tag":{"415":"contact","454":"contact-us"},"site-pages-type":"free","site-pages-page-builder":"gutenberg","site-pages-category":[],"site-pages-parent-category":{"60":"business","61":"free"},"required-plugins":[{"slug":"ultimate-addons-for-gutenberg","init":"ultimate-addons-for-gutenberg\/ultimate-addons-for-gutenberg.php","name":"Spectra"},{"slug":"sureforms","init":"sureforms\/sureforms.php","name":"SureForms"}],"spectra-ver":[]}},"spectra-ver":[],"query_args":{"post_type":"astra-sites","post_status":["publish"],"fields":"ids","no_found_rows":true,"paged":29,"posts_per_page":15,"tax_query":{"relation":"AND","0":{"relation":"OR","0":{"taxonomy":"spectra-blocks-ver","field":"slug","terms":["v2","v3"],"operator":"IN"},"1":{"taxonomy":"spectra-blocks-ver","operator":"NOT EXISTS"}},"1":{"taxonomy":"astra-sites-type","field":"slug","terms":["siteground"],"operator":"NOT IN"}},"orderby":"menu_order","order":"ASC"},"related-bb-template":"","related-elementor-template":"","related-gutenberg-template":"","related_ecommerce_template":0,"ecommerce_parent_template":""},"id-86333":{"title":"Martial Arts School","id":86333,"publish-date":1708616948,"featured-image-url":"https:\/\/websitedemos.net\/wp-content\/uploads\/2024\/02\/martial-arts-07.jpg","thumbnail-image-url":"https:\/\/websitedemos.net\/wp-content\/uploads\/2024\/02\/martial-arts-07-600x2920.jpg","fullpage-thumbnail-image-url":"https:\/\/websitedemos.net\/wp-content\/uploads\/2024\/02\/martial-arts-07-400x1947.jpg","astra-site-url":"\/\/websitedemos.net\/martial-arts-07","astra-site-parent-id":3490,"astra-sites-tag":{"3420":"black","3419":"dark","1804":"karate","1803":"kung-fu","1801":"martial-arts","1805":"mixed-martial-arts","3418":"mobile-friendly","1844":"premium","3417":"responsive","1802":"self-defence"},"astra-sites-type":"agency-mini","astra-site-category":{"27":"business"},"astra-sites-template-category":{"2825":"coaching","2772":"education","2782":"school","2873":"tutor"},"astra-site-page-builder":"gutenberg","categories":[],"required-plugins":[{"slug":"ultimate-addons-for-gutenberg","init":"ultimate-addons-for-gutenberg\/ultimate-addons-for-gutenberg.php","name":"Spectra"},{"slug":"sureforms","init":"sureforms\/sureforms.php","name":"SureForms"}],"post-status":"publish","post-content":"","post-excerpt":"","pages":{"id-86336":{"title":"Home","featured-image-url":"https:\/\/websitedemos.net\/wp-content\/uploads\/2024\/02\/martial-arts-07.jpg","thumbnail-image-url":"https:\/\/websitedemos.net\/wp-content\/uploads\/2024\/02\/martial-arts-07-600x2920.jpg","astra-page-api-url":"https:\/\/websitedemos.net\/martial-arts-07\/wp-json\/wp\/v2\/pages\/247","dynamic-page":"no","astra-page-url":"\/\/websitedemos.net\/martial-arts-07\/","astra-sites-tag":{"423":"home"},"site-pages-type":"agency-mini","site-pages-page-builder":"gutenberg","site-pages-category":[],"site-pages-parent-category":{"60":"business"},"required-plugins":[{"slug":"ultimate-addons-for-gutenberg","init":"ultimate-addons-for-gutenberg\/ultimate-addons-for-gutenberg.php","name":"Spectra"}],"spectra-ver":[]},"id-86334":{"title":"About Us","featured-image-url":"https:\/\/websitedemos.net\/wp-content\/uploads\/2024\/02\/martial-arts-07-about-us.jpg","thumbnail-image-url":"https:\/\/websitedemos.net\/wp-content\/uploads\/2024\/02\/martial-arts-07-about-us-600x2342.jpg","astra-page-api-url":"https:\/\/websitedemos.net\/martial-arts-07\/wp-json\/wp\/v2\/pages\/248","dynamic-page":"no","astra-page-url":"\/\/websitedemos.net\/martial-arts-07\/about-us\/","astra-sites-tag":{"352":"about"},"site-pages-type":"agency-mini","site-pages-page-builder":"gutenberg","site-pages-category":[],"site-pages-parent-category":{"60":"business"},"required-plugins":[{"slug":"ultimate-addons-for-gutenberg","init":"ultimate-addons-for-gutenberg\/ultimate-addons-for-gutenberg.php","name":"Spectra"}],"spectra-ver":[]},"id-86337":{"title":"Programs","featured-image-url":"https:\/\/websitedemos.net\/wp-content\/uploads\/2024\/02\/martial-arts-07-programs.jpg","thumbnail-image-url":"https:\/\/websitedemos.net\/wp-content\/uploads\/2024\/02\/martial-arts-07-programs-600x1810.jpg","astra-page-api-url":"https:\/\/websitedemos.net\/martial-arts-07\/wp-json\/wp\/v2\/pages\/249","dynamic-page":"no","astra-page-url":"\/\/websitedemos.net\/martial-arts-07\/programs\/","astra-sites-tag":{"989":"programs"},"site-pages-type":"agency-mini","site-pages-page-builder":"gutenberg","site-pages-category":[],"site-pages-parent-category":{"60":"business"},"required-plugins":[{"slug":"ultimate-addons-for-gutenberg","init":"ultimate-addons-for-gutenberg\/ultimate-addons-for-gutenberg.php","name":"Spectra"}],"spectra-ver":[]},"id-86338":{"title":"Testimonials","featured-image-url":"https:\/\/websitedemos.net\/wp-content\/uploads\/2024\/02\/martial-arts-07-testimonials.jpg","thumbnail-image-url":"https:\/\/websitedemos.net\/wp-content\/uploads\/2024\/02\/martial-arts-07-testimonials-600x1408.jpg","astra-page-api-url":"https:\/\/websitedemos.net\/martial-arts-07\/wp-json\/wp\/v2\/pages\/250","dynamic-page":"no","astra-page-url":"\/\/websitedemos.net\/martial-arts-07\/testimonials\/","astra-sites-tag":{"433":"testimonials"},"site-pages-type":"agency-mini","site-pages-page-builder":"gutenberg","site-pages-category":[],"site-pages-parent-category":{"60":"business"},"required-plugins":[{"slug":"ultimate-addons-for-gutenberg","init":"ultimate-addons-for-gutenberg\/ultimate-addons-for-gutenberg.php","name":"Spectra"}],"spectra-ver":[]},"id-86335":{"title":"Contact Us","featured-image-url":"https:\/\/websitedemos.net\/wp-content\/uploads\/2024\/02\/martial-arts-07-contact-us.jpg","thumbnail-image-url":"https:\/\/websitedemos.net\/wp-content\/uploads\/2024\/02\/martial-arts-07-contact-us-600x1218.jpg","astra-page-api-url":"https:\/\/websitedemos.net\/martial-arts-07\/wp-json\/wp\/v2\/pages\/251","dynamic-page":"no","astra-page-url":"\/\/websitedemos.net\/martial-arts-07\/contact-us\/","astra-sites-tag":{"415":"contact"},"site-pages-type":"agency-mini","site-pages-page-builder":"gutenberg","site-pages-category":[],"site-pages-parent-category":{"60":"business"},"required-plugins":[{"slug":"ultimate-addons-for-gutenberg","init":"ultimate-addons-for-gutenberg\/ultimate-addons-for-gutenberg.php","name":"Spectra"},{"slug":"sureforms","init":"sureforms\/sureforms.php","name":"SureForms"}],"spectra-ver":[]}},"spectra-ver":[],"query_args":{"post_type":"astra-sites","post_status":["publish"],"fields":"ids","no_found_rows":true,"paged":29,"posts_per_page":15,"tax_query":{"relation":"AND","0":{"relation":"OR","0":{"taxonomy":"spectra-blocks-ver","field":"slug","terms":["v2","v3"],"operator":"IN"},"1":{"taxonomy":"spectra-blocks-ver","operator":"NOT EXISTS"}},"1":{"taxonomy":"astra-sites-type","field":"slug","terms":["siteground"],"operator":"NOT IN"}},"orderby":"menu_order","order":"ASC"},"related-bb-template":"","related-elementor-template":"","related-gutenberg-template":"","related_ecommerce_template":0,"ecommerce_parent_template":""},"id-57399":{"title":"Sports Wear Store","id":57399,"publish-date":1630001801,"featured-image-url":"https:\/\/websitedemos.net\/wp-content\/uploads\/2021\/08\/sports-wear-store-04-home.jpg","thumbnail-image-url":"https:\/\/websitedemos.net\/wp-content\/uploads\/2021\/08\/sports-wear-store-04-home.jpg","fullpage-thumbnail-image-url":"https:\/\/websitedemos.net\/wp-content\/uploads\/2021\/08\/sports-wear-store-04-home.jpg","astra-site-url":"\/\/websitedemos.net\/sports-wear-store-04","astra-site-parent-id":2337,"astra-sites-tag":{"2418":"commerce","1017":"e-commerce","496":"ecommerce","3416":"elementor","2419":"eshopping","2422":"online-market","732":"online-shop","2420":"online-shopping","383":"online-store","1844":"premium","2421":"purchases","2417":"reseller","733":"shop","2416":"shopping","2344":"sports-gear","2339":"sports-wear","2345":"sports-wear-and-gear","749":"store","1024":"woocommerce"},"astra-sites-type":"agency-mini","astra-site-category":{"27":"business","38":"ecommerce"},"astra-sites-template-category":{"2777":"business","2769":"ecommerce","2857":"online-shopping","2826":"sports"},"astra-site-page-builder":"elementor","categories":{"3427":"default","2495":"ecommerce","3432":"game","3429":"premium"},"required-plugins":[{"slug":"elementor","init":"elementor\/elementor.php","name":"Elementor"},{"slug":"header-footer-elementor","init":"header-footer-elementor\/header-footer-elementor.php","name":"Ultimate Addons for Elementor (UAE)"},{"slug":"woocommerce","init":"woocommerce\/woocommerce.php","name":"WooCommerce"},{"slug":"astra-addon","init":"astra-addon\/astra-addon.php","name":"Astra Pro"},{"slug":"variation-swatches-woo","init":"variation-swatches-woo\/variation-swatches-woo.php","name":"Variation Swatches for WooCommerce"},{"slug":"woocommerce-payments","init":"woocommerce-payments\/woocommerce-payments.php","name":"WooPayments"},{"slug":"cartflows","init":"cartflows\/cartflows.php","name":"CartFlows"},{"slug":"woo-cart-abandonment-recovery","init":"woo-cart-abandonment-recovery\/woo-cart-abandonment-recovery.php","name":"Cart Abandonment Recovery for WooCommerce"},{"slug":"sureforms","init":"sureforms\/sureforms.php","name":"SureForms"}],"post-status":"publish","post-content":"<!-- wp:paragraph -->\n<p>Want to build an online sportswear store? Or maybe even revamp an existing one. With our Sports Wear Store web template, you can launch a fully-fledged store quickly and easily. The templates come fully integrated with WooCommerce, making it easy to sell online.<\/p>\n<!-- \/wp:paragraph -->\n\n<!-- wp:paragraph -->\n<p>The impressive template allows you to showcase products based on the sports category, gender, latest arrivals, and more. Additionally, you can feature all the top deals as well.<\/p>\n<!-- \/wp:paragraph -->\n\n<!-- wp:heading -->\n<h2>Key features of the Sports Wear Store template<\/h2>\n<!-- \/wp:heading -->\n\n<!-- wp:list -->\n<ul><li>Well-designed template that has all the correct elements in the right place<\/li><li>Dedicated template to showcase the best deals and offers<\/li><li>Display products based on categories, such as sports, gender, and best sellers<\/li><li>Newsletter subscription form integrated across the website templates<\/li><li>Full compatibility with leading page builders<\/li><\/ul>\n<!-- \/wp:list -->","post-excerpt":"Perfect website template for building a highly engaging online sportswear store","pages":{"id-57402":{"title":"Home","featured-image-url":"https:\/\/websitedemos.net\/wp-content\/uploads\/2021\/08\/sports-wear-store-04-home.jpg","thumbnail-image-url":"https:\/\/websitedemos.net\/wp-content\/uploads\/2021\/08\/sports-wear-store-04-home.jpg","astra-page-api-url":"https:\/\/websitedemos.net\/sports-wear-store-04\/wp-json\/wp\/v2\/pages\/15","dynamic-page":"yes","astra-page-url":"\/\/websitedemos.net\/sports-wear-store-04\/","astra-sites-tag":{"423":"home"},"site-pages-type":"agency-mini","site-pages-page-builder":"elementor","site-pages-category":[],"site-pages-parent-category":{"60":"business","64":"ecommerce"},"required-plugins":[{"slug":"astra-addon","init":"astra-addon\/astra-addon.php","name":"Astra Pro"},{"slug":"elementor","init":"elementor\/elementor.php","name":"Elementor"},{"slug":"header-footer-elementor","init":"header-footer-elementor\/header-footer-elementor.php","name":"Ultimate Addons for Elementor (UAE)"},{"slug":"variation-swatches-woo","init":"variation-swatches-woo\/variation-swatches-woo.php","name":"Variation Swatches for WooCommerce"},{"slug":"woocommerce","init":"woocommerce\/woocommerce.php","name":"WooCommerce"},{"slug":"woocommerce-payments","init":"woocommerce-payments\/woocommerce-payments.php","name":"WooPayments"}],"spectra-ver":[]},"id-57403":{"title":"Top Deals","featured-image-url":"https:\/\/websitedemos.net\/wp-content\/uploads\/2021\/08\/sports-wear-store-04-top-deals.jpg","thumbnail-image-url":"https:\/\/websitedemos.net\/wp-content\/uploads\/2021\/08\/sports-wear-store-04-top-deals.jpg","astra-page-api-url":"https:\/\/websitedemos.net\/sports-wear-store-04\/wp-json\/wp\/v2\/pages\/389","dynamic-page":"no","astra-page-url":"\/\/websitedemos.net\/sports-wear-store-04\/top-deals\/","astra-sites-tag":{"2063":"sales","2338":"top-deals"},"site-pages-type":"agency-mini","site-pages-page-builder":"elementor","site-pages-category":[],"site-pages-parent-category":{"60":"business","64":"ecommerce"},"required-plugins":[{"slug":"astra-addon","init":"astra-addon\/astra-addon.php","name":"Astra Pro"},{"slug":"elementor","init":"elementor\/elementor.php","name":"Elementor"},{"slug":"header-footer-elementor","init":"header-footer-elementor\/header-footer-elementor.php","name":"Ultimate Addons for Elementor (UAE)"}],"spectra-ver":[]},"id-57400":{"title":"About","featured-image-url":"https:\/\/websitedemos.net\/wp-content\/uploads\/2021\/08\/sports-wear-store-04-about.jpg","thumbnail-image-url":"https:\/\/websitedemos.net\/wp-content\/uploads\/2021\/08\/sports-wear-store-04-about.jpg","astra-page-api-url":"https:\/\/websitedemos.net\/sports-wear-store-04\/wp-json\/wp\/v2\/pages\/533","dynamic-page":"no","astra-page-url":"\/\/websitedemos.net\/sports-wear-store-04\/about\/","astra-sites-tag":{"352":"about"},"site-pages-type":"agency-mini","site-pages-page-builder":"elementor","site-pages-category":[],"site-pages-parent-category":{"60":"business","64":"ecommerce"},"required-plugins":[{"slug":"astra-addon","init":"astra-addon\/astra-addon.php","name":"Astra Pro"},{"slug":"elementor","init":"elementor\/elementor.php","name":"Elementor"},{"slug":"header-footer-elementor","init":"header-footer-elementor\/header-footer-elementor.php","name":"Ultimate Addons for Elementor (UAE)"}],"spectra-ver":[]},"id-57401":{"title":"Contact","featured-image-url":"https:\/\/websitedemos.net\/wp-content\/uploads\/2021\/08\/sports-wear-store-04-contact.jpg","thumbnail-image-url":"https:\/\/websitedemos.net\/wp-content\/uploads\/2021\/08\/sports-wear-store-04-contact.jpg","astra-page-api-url":"https:\/\/websitedemos.net\/sports-wear-store-04\/wp-json\/wp\/v2\/pages\/658","dynamic-page":"no","astra-page-url":"\/\/websitedemos.net\/sports-wear-store-04\/contact\/","astra-sites-tag":{"415":"contact"},"site-pages-type":"agency-mini","site-pages-page-builder":"elementor","site-pages-category":[],"site-pages-parent-category":{"60":"business","64":"ecommerce"},"required-plugins":[{"slug":"astra-addon","init":"astra-addon\/astra-addon.php","name":"Astra Pro"},{"slug":"elementor","init":"elementor\/elementor.php","name":"Elementor"},{"slug":"sureforms","init":"sureforms\/sureforms.php","name":"SureForms"},{"slug":"header-footer-elementor","init":"header-footer-elementor\/header-footer-elementor.php","name":"Ultimate Addons for Elementor (UAE)"}],"spectra-ver":[]}},"spectra-ver":[],"query_args":{"post_type":"astra-sites","post_status":["publish"],"fields":"ids","no_found_rows":true,"paged":29,"posts_per_page":15,"tax_query":{"relation":"AND","0":{"relation":"OR","0":{"taxonomy":"spectra-blocks-ver","field":"slug","terms":["v2","v3"],"operator":"IN"},"1":{"taxonomy":"spectra-blocks-ver","operator":"NOT EXISTS"}},"1":{"taxonomy":"astra-sites-type","field":"slug","terms":["siteground"],"operator":"NOT IN"}},"orderby":"menu_order","order":"ASC"},"related-bb-template":"","related-elementor-template":57399,"related-gutenberg-template":85715,"related_ecommerce_template":0,"ecommerce_parent_template":""},"id-47932":{"title":"Online Health Coach","id":47932,"publish-date":1603823106,"featured-image-url":"https:\/\/websitedemos.net\/wp-content\/uploads\/2020\/10\/online-health-08.jpg","thumbnail-image-url":"https:\/\/websitedemos.net\/wp-content\/uploads\/2020\/10\/online-health-08-600x1990.jpg","fullpage-thumbnail-image-url":"https:\/\/websitedemos.net\/wp-content\/uploads\/2020\/10\/online-health-08-400x1327.jpg","astra-site-url":"\/\/websitedemos.net\/online-health-coach-08","astra-site-parent-id":1684,"astra-sites-tag":{"462":"courses","469":"ecourse","468":"elearning","518":"health-coach","467":"learndash","460":"learning","466":"online-courses","975":"online-learning"},"astra-sites-type":"free","astra-site-category":{"27":"business","39":"free"},"astra-sites-template-category":[],"astra-site-page-builder":"gutenberg","categories":{"2494":"elearning"},"required-plugins":[{"slug":"ultimate-addons-for-gutenberg","init":"ultimate-addons-for-gutenberg\/ultimate-addons-for-gutenberg.php","name":"Spectra"},{"slug":"sfwd-lms","init":"sfwd-lms\/sfwd_lms.php","name":"LearnDash LMS"},{"slug":"learndash-course-grid","init":"learndash-course-grid\/learndash_course_grid.php","name":"LearnDash LMS - Course Grid"},{"slug":"presto-player","init":"presto-player\/presto-player.php","name":"Presto Player"},{"slug":"sureforms","init":"sureforms\/sureforms.php","name":"SureForms"}],"post-status":"publish","post-content":"","post-excerpt":"","pages":{"id-47941":{"title":"Home","featured-image-url":"https:\/\/websitedemos.net\/wp-content\/uploads\/2020\/10\/online-health-08.jpg","thumbnail-image-url":"https:\/\/websitedemos.net\/wp-content\/uploads\/2020\/10\/online-health-08-600x1990.jpg","astra-page-api-url":"https:\/\/websitedemos.net\/online-health-coach-08\/wp-json\/wp\/v2\/pages\/24365","dynamic-page":"no","astra-page-url":"\/\/websitedemos.net\/online-health-coach-08\/","astra-sites-tag":{"423":"home"},"site-pages-type":"free","site-pages-page-builder":"gutenberg","site-pages-category":[],"site-pages-parent-category":{"60":"business","61":"free"},"required-plugins":[{"slug":"ultimate-addons-for-gutenberg","init":"ultimate-addons-for-gutenberg\/ultimate-addons-for-gutenberg.php","name":"Spectra"}],"spectra-ver":[]},"id-47939":{"title":"All Courses","featured-image-url":"https:\/\/websitedemos.net\/wp-content\/uploads\/2020\/10\/online-health-08-courses.jpg","thumbnail-image-url":"https:\/\/websitedemos.net\/wp-content\/uploads\/2020\/10\/online-health-08-courses-600x954.jpg","astra-page-api-url":"https:\/\/websitedemos.net\/online-health-coach-08\/wp-json\/wp\/v2\/pages\/24366","dynamic-page":"yes","astra-page-url":"\/\/websitedemos.net\/online-health-coach-08\/all-courses\/","astra-sites-tag":{"462":"courses"},"site-pages-type":"free","site-pages-page-builder":"gutenberg","site-pages-category":[],"site-pages-parent-category":{"60":"business","61":"free"},"required-plugins":[{"slug":"sfwd-lms","init":"sfwd-lms\/sfwd_lms.php","name":"LearnDash LMS"},{"slug":"learndash-course-grid","init":"learndash-course-grid\/learndash_course_grid.php","name":"LearnDash LMS - Course Grid"},{"slug":"ultimate-addons-for-gutenberg","init":"ultimate-addons-for-gutenberg\/ultimate-addons-for-gutenberg.php","name":"Spectra"}],"spectra-ver":[]},"id-47938":{"title":"About","featured-image-url":"https:\/\/websitedemos.net\/wp-content\/uploads\/2020\/10\/online-health-08-about.jpg","thumbnail-image-url":"https:\/\/websitedemos.net\/wp-content\/uploads\/2020\/10\/online-health-08-about-600x1541.jpg","astra-page-api-url":"https:\/\/websitedemos.net\/online-health-coach-08\/wp-json\/wp\/v2\/pages\/24368","dynamic-page":"no","astra-page-url":"\/\/websitedemos.net\/online-health-coach-08\/about\/","astra-sites-tag":{"352":"about"},"site-pages-type":"free","site-pages-page-builder":"gutenberg","site-pages-category":[],"site-pages-parent-category":{"60":"business","61":"free"},"required-plugins":[{"slug":"ultimate-addons-for-gutenberg","init":"ultimate-addons-for-gutenberg\/ultimate-addons-for-gutenberg.php","name":"Spectra"}],"spectra-ver":[]},"id-47940":{"title":"Contact","featured-image-url":"https:\/\/websitedemos.net\/wp-content\/uploads\/2020\/10\/online-health-08-contact.jpg","thumbnail-image-url":"https:\/\/websitedemos.net\/wp-content\/uploads\/2020\/10\/online-health-08-contact-600x734.jpg","astra-page-api-url":"https:\/\/websitedemos.net\/online-health-coach-08\/wp-json\/wp\/v2\/pages\/24369","dynamic-page":"no","astra-page-url":"\/\/websitedemos.net\/online-health-coach-08\/contact\/","astra-sites-tag":{"415":"contact"},"site-pages-type":"free","site-pages-page-builder":"gutenberg","site-pages-category":[],"site-pages-parent-category":{"60":"business","61":"free"},"required-plugins":[{"slug":"ultimate-addons-for-gutenberg","init":"ultimate-addons-for-gutenberg\/ultimate-addons-for-gutenberg.php","name":"Spectra"},{"slug":"sureforms","init":"sureforms\/sureforms.php","name":"SureForms"}],"spectra-ver":[]}},"spectra-ver":[],"query_args":{"post_type":"astra-sites","post_status":["publish"],"fields":"ids","no_found_rows":true,"paged":29,"posts_per_page":15,"tax_query":{"relation":"AND","0":{"relation":"OR","0":{"taxonomy":"spectra-blocks-ver","field":"slug","terms":["v2","v3"],"operator":"IN"},"1":{"taxonomy":"spectra-blocks-ver","operator":"NOT EXISTS"}},"1":{"taxonomy":"astra-sites-type","field":"slug","terms":["siteground"],"operator":"NOT IN"}},"orderby":"menu_order","order":"ASC"},"related-bb-template":"","related-elementor-template":"","related-gutenberg-template":"","related_ecommerce_template":0,"ecommerce_parent_template":""},"id-86325":{"title":"University","id":86325,"publish-date":1708606400,"featured-image-url":"https:\/\/websitedemos.net\/wp-content\/uploads\/2024\/02\/university-07.jpg","thumbnail-image-url":"https:\/\/websitedemos.net\/wp-content\/uploads\/2024\/02\/university-07-600x2465.jpg","fullpage-thumbnail-image-url":"https:\/\/websitedemos.net\/wp-content\/uploads\/2024\/02\/university-07-400x1643.jpg","astra-site-url":"\/\/websitedemos.net\/university-07","astra-site-parent-id":3489,"astra-sites-tag":{"457":"college","459":"education","460":"learning","1844":"premium","456":"school","458":"university"},"astra-sites-type":"agency-mini","astra-site-category":{"27":"business"},"astra-sites-template-category":{"2840":"college-university","2772":"education","2782":"school"},"astra-site-page-builder":"gutenberg","categories":{"2491":"educational-institutes"},"required-plugins":[{"slug":"ultimate-addons-for-gutenberg","init":"ultimate-addons-for-gutenberg\/ultimate-addons-for-gutenberg.php","name":"Spectra"},{"slug":"sureforms","init":"sureforms\/sureforms.php","name":"SureForms"}],"post-status":"publish","post-content":"","post-excerpt":"","pages":{"id-86330":{"title":"Home","featured-image-url":"https:\/\/websitedemos.net\/wp-content\/uploads\/2024\/02\/university-07.jpg","thumbnail-image-url":"https:\/\/websitedemos.net\/wp-content\/uploads\/2024\/02\/university-07-600x2465.jpg","astra-page-api-url":"https:\/\/websitedemos.net\/university-07\/wp-json\/wp\/v2\/pages\/503","dynamic-page":"no","astra-page-url":"\/\/websitedemos.net\/university-07\/","astra-sites-tag":{"423":"home"},"site-pages-type":"agency-mini","site-pages-page-builder":"gutenberg","site-pages-category":[],"site-pages-parent-category":{"60":"business"},"required-plugins":[{"slug":"ultimate-addons-for-gutenberg","init":"ultimate-addons-for-gutenberg\/ultimate-addons-for-gutenberg.php","name":"Spectra"}],"spectra-ver":[]},"id-86326":{"title":"About","featured-image-url":"https:\/\/websitedemos.net\/wp-content\/uploads\/2024\/02\/university-07-about.jpg","thumbnail-image-url":"https:\/\/websitedemos.net\/wp-content\/uploads\/2024\/02\/university-07-about-600x2351.jpg","astra-page-api-url":"https:\/\/websitedemos.net\/university-07\/wp-json\/wp\/v2\/pages\/506","dynamic-page":"no","astra-page-url":"\/\/websitedemos.net\/university-07\/about\/","astra-sites-tag":{"352":"about"},"site-pages-type":"agency-mini","site-pages-page-builder":"gutenberg","site-pages-category":[],"site-pages-parent-category":{"60":"business"},"required-plugins":[{"slug":"ultimate-addons-for-gutenberg","init":"ultimate-addons-for-gutenberg\/ultimate-addons-for-gutenberg.php","name":"Spectra"}],"spectra-ver":[]},"id-86328":{"title":"Courses","featured-image-url":"https:\/\/websitedemos.net\/wp-content\/uploads\/2024\/02\/university-07-course.jpg","thumbnail-image-url":"https:\/\/websitedemos.net\/wp-content\/uploads\/2024\/02\/university-07-course-600x1703.jpg","astra-page-api-url":"https:\/\/websitedemos.net\/university-07\/wp-json\/wp\/v2\/pages\/509","dynamic-page":"no","astra-page-url":"\/\/websitedemos.net\/university-07\/courses\/","astra-sites-tag":{"462":"courses"},"site-pages-type":"agency-mini","site-pages-page-builder":"gutenberg","site-pages-category":[],"site-pages-parent-category":{"60":"business"},"required-plugins":[{"slug":"ultimate-addons-for-gutenberg","init":"ultimate-addons-for-gutenberg\/ultimate-addons-for-gutenberg.php","name":"Spectra"}],"spectra-ver":[]},"id-86331":{"title":"Teachers","featured-image-url":"https:\/\/websitedemos.net\/wp-content\/uploads\/2024\/02\/university-07-teachers.jpg","thumbnail-image-url":"https:\/\/websitedemos.net\/wp-content\/uploads\/2024\/02\/university-07-teachers-600x1262.jpg","astra-page-api-url":"https:\/\/websitedemos.net\/university-07\/wp-json\/wp\/v2\/pages\/511","dynamic-page":"no","astra-page-url":"\/\/websitedemos.net\/university-07\/teachers\/","astra-sites-tag":{"2750":"teachers"},"site-pages-type":"agency-mini","site-pages-page-builder":"gutenberg","site-pages-category":[],"site-pages-parent-category":{"60":"business"},"required-plugins":[{"slug":"ultimate-addons-for-gutenberg","init":"ultimate-addons-for-gutenberg\/ultimate-addons-for-gutenberg.php","name":"Spectra"}],"spectra-ver":[]},"id-86329":{"title":"Gallery","featured-image-url":"https:\/\/websitedemos.net\/wp-content\/uploads\/2024\/02\/university-07-gallery.jpg","thumbnail-image-url":"https:\/\/websitedemos.net\/wp-content\/uploads\/2024\/02\/university-07-gallery-600x1407.jpg","astra-page-api-url":"https:\/\/websitedemos.net\/university-07\/wp-json\/wp\/v2\/pages\/513","dynamic-page":"no","astra-page-url":"\/\/websitedemos.net\/university-07\/gallery\/","astra-sites-tag":{"461":"gallery"},"site-pages-type":"agency-mini","site-pages-page-builder":"gutenberg","site-pages-category":[],"site-pages-parent-category":{"60":"business"},"required-plugins":[{"slug":"ultimate-addons-for-gutenberg","init":"ultimate-addons-for-gutenberg\/ultimate-addons-for-gutenberg.php","name":"Spectra"}],"spectra-ver":[]},"id-86327":{"title":"Contact","featured-image-url":"https:\/\/websitedemos.net\/wp-content\/uploads\/2024\/02\/university-07-contact.jpg","thumbnail-image-url":"https:\/\/websitedemos.net\/wp-content\/uploads\/2024\/02\/university-07-contact-600x1090.jpg","astra-page-api-url":"https:\/\/websitedemos.net\/university-07\/wp-json\/wp\/v2\/pages\/515","dynamic-page":"no","astra-page-url":"\/\/websitedemos.net\/university-07\/contact\/","astra-sites-tag":{"415":"contact"},"site-pages-type":"agency-mini","site-pages-page-builder":"gutenberg","site-pages-category":[],"site-pages-parent-category":{"60":"business"},"required-plugins":[{"slug":"ultimate-addons-for-gutenberg","init":"ultimate-addons-for-gutenberg\/ultimate-addons-for-gutenberg.php","name":"Spectra"},{"slug":"sureforms","init":"sureforms\/sureforms.php","name":"SureForms"}],"spectra-ver":[]}},"spectra-ver":[],"query_args":{"post_type":"astra-sites","post_status":["publish"],"fields":"ids","no_found_rows":true,"paged":29,"posts_per_page":15,"tax_query":{"relation":"AND","0":{"relation":"OR","0":{"taxonomy":"spectra-blocks-ver","field":"slug","terms":["v2","v3"],"operator":"IN"},"1":{"taxonomy":"spectra-blocks-ver","operator":"NOT EXISTS"}},"1":{"taxonomy":"astra-sites-type","field":"slug","terms":["siteground"],"operator":"NOT IN"}},"orderby":"menu_order","order":"ASC"},"related-bb-template":"","related-elementor-template":"","related-gutenberg-template":"","related_ecommerce_template":0,"ecommerce_parent_template":""},"id-58864":{"title":"Flute Artist","id":58864,"publish-date":1643645073,"featured-image-url":"https:\/\/websitedemos.net\/wp-content\/uploads\/2022\/01\/flute-artist-02-home.jpg","thumbnail-image-url":"https:\/\/websitedemos.net\/wp-content\/uploads\/2022\/01\/flute-artist-02-home.jpg","fullpage-thumbnail-image-url":"https:\/\/websitedemos.net\/wp-content\/uploads\/2022\/01\/flute-artist-02-home.jpg","astra-site-url":"\/\/websitedemos.net\/flute-artist-02","astra-site-parent-id":2502,"astra-sites-tag":{"339":"artist","3416":"elementor","2438":"flute-artist","2439":"flute-player","2503":"grooved","407":"music","2504":"musical-instrument-player"},"astra-sites-type":"free","astra-site-category":{"27":"business","39":"free"},"astra-sites-template-category":{"2802":"artist","2781":"music"},"astra-site-page-builder":"elementor","categories":{"2486":"art-music","3427":"default","3428":"free","2488":"portfolio"},"required-plugins":[{"slug":"elementor","init":"elementor\/elementor.php","name":"Elementor"},{"slug":"wpforms-lite","init":"wpforms-lite\/wpforms.php","name":"WPForms Lite"},{"slug":"sureforms","init":"sureforms\/sureforms.php","name":"SureForms"}],"post-status":"publish","post-content":"<!-- wp:paragraph -->\n<p>The Flute Artist template has been designed to reflect the elegance and classic nature of the instrument and the industry. It\u2019s a very calm layout with sober colors and an instant appeal.<\/p>\n<!-- \/wp:paragraph -->\n\n<!-- wp:paragraph -->\n<p>The homepage begins dark and quickly opens out to include lots of white space, modern, elegant fonts and lots of imagery to set the scene. There are also options to include video and audio clips, a biography page, portfolio page and contact form.<\/p>\n<!-- \/wp:paragraph -->\n\n<!-- wp:heading -->\n<h2>Key features of the Flute Artist template<\/h2>\n<!-- \/wp:heading -->\n\n<!-- wp:list -->\n<ul><li>Flexible portfolio website for musicians<\/li><li>Elegant design ideal for the niche<\/li><li>Includes the option to add audio and video<\/li><li>Dedicated portfolio and contact page<\/li><li>Flexible layout that can be fully customized<\/li><li>Page builder compatible for ease of use<\/li><\/ul>\n<!-- \/wp:list -->","post-excerpt":"A very elegant musician template designed to appeal to the widest possible audience","pages":{"id-58448":{"title":"Home","featured-image-url":"https:\/\/websitedemos.net\/wp-content\/uploads\/2022\/01\/flute-artist-02-home.jpg","thumbnail-image-url":"https:\/\/websitedemos.net\/wp-content\/uploads\/2022\/01\/flute-artist-02-home.jpg","astra-page-api-url":"https:\/\/websitedemos.net\/flute-artist-02\/wp-json\/wp\/v2\/pages\/24","dynamic-page":"no","astra-page-url":"\/\/websitedemos.net\/flute-artist-02\/","astra-sites-tag":{"423":"home"},"site-pages-type":"free","site-pages-page-builder":"elementor","site-pages-category":[],"site-pages-parent-category":{"60":"business","61":"free"},"required-plugins":[{"slug":"elementor","init":"elementor\/elementor.php","name":"Elementor"}],"spectra-ver":[]},"id-58445":{"title":"Biography","featured-image-url":"https:\/\/websitedemos.net\/wp-content\/uploads\/2022\/01\/flute-artist-02-biography.jpg","thumbnail-image-url":"https:\/\/websitedemos.net\/wp-content\/uploads\/2022\/01\/flute-artist-02-biography.jpg","astra-page-api-url":"https:\/\/websitedemos.net\/flute-artist-02\/wp-json\/wp\/v2\/pages\/26","dynamic-page":"no","astra-page-url":"\/\/websitedemos.net\/flute-artist-02\/biography\/","astra-sites-tag":{"1566":"biography"},"site-pages-type":"free","site-pages-page-builder":"elementor","site-pages-category":[],"site-pages-parent-category":{"60":"business","61":"free"},"required-plugins":[{"slug":"elementor","init":"elementor\/elementor.php","name":"Elementor"}],"spectra-ver":[]},"id-58447":{"title":"Gallery","featured-image-url":"https:\/\/websitedemos.net\/wp-content\/uploads\/2022\/01\/flute-artist-02-gallery.jpg","thumbnail-image-url":"https:\/\/websitedemos.net\/wp-content\/uploads\/2022\/01\/flute-artist-02-gallery.jpg","astra-page-api-url":"https:\/\/websitedemos.net\/flute-artist-02\/wp-json\/wp\/v2\/pages\/28","dynamic-page":"no","astra-page-url":"\/\/websitedemos.net\/flute-artist-02\/gallery\/","astra-sites-tag":{"461":"gallery"},"site-pages-type":"free","site-pages-page-builder":"elementor","site-pages-category":[],"site-pages-parent-category":{"60":"business","61":"free"},"required-plugins":[{"slug":"elementor","init":"elementor\/elementor.php","name":"Elementor"}],"spectra-ver":[]},"id-58446":{"title":"Contact","featured-image-url":"https:\/\/websitedemos.net\/wp-content\/uploads\/2022\/01\/flute-artist-02-contact.jpg","thumbnail-image-url":"https:\/\/websitedemos.net\/wp-content\/uploads\/2022\/01\/flute-artist-02-contact.jpg","astra-page-api-url":"https:\/\/websitedemos.net\/flute-artist-02\/wp-json\/wp\/v2\/pages\/32","dynamic-page":"no","astra-page-url":"\/\/websitedemos.net\/flute-artist-02\/contact\/","astra-sites-tag":{"415":"contact"},"site-pages-type":"free","site-pages-page-builder":"elementor","site-pages-category":[],"site-pages-parent-category":{"60":"business","61":"free"},"required-plugins":[{"slug":"elementor","init":"elementor\/elementor.php","name":"Elementor"},{"slug":"sureforms","init":"sureforms\/sureforms.php","name":"SureForms"}],"spectra-ver":[]}},"spectra-ver":[],"query_args":{"post_type":"astra-sites","post_status":["publish"],"fields":"ids","no_found_rows":true,"paged":29,"posts_per_page":15,"tax_query":{"relation":"AND","0":{"relation":"OR","0":{"taxonomy":"spectra-blocks-ver","field":"slug","terms":["v2","v3"],"operator":"IN"},"1":{"taxonomy":"spectra-blocks-ver","operator":"NOT EXISTS"}},"1":{"taxonomy":"astra-sites-type","field":"slug","terms":["siteground"],"operator":"NOT IN"}},"orderby":"menu_order","order":"ASC"},"related-bb-template":"","related-elementor-template":58864,"related-gutenberg-template":68088,"related_ecommerce_template":0,"ecommerce_parent_template":""},"id-48431":{"title":"Simply Natural","id":48431,"publish-date":1603963839,"featured-image-url":"https:\/\/websitedemos.net\/wp-content\/uploads\/2020\/10\/plant-store-08.jpg","thumbnail-image-url":"https:\/\/websitedemos.net\/wp-content\/uploads\/2020\/10\/plant-store-08-600x2263.jpg","fullpage-thumbnail-image-url":"https:\/\/websitedemos.net\/wp-content\/uploads\/2020\/10\/plant-store-08-400x1508.jpg","astra-site-url":"\/\/websitedemos.net\/plant-store-08","astra-site-parent-id":1732,"astra-sites-tag":{"2418":"commerce","1017":"e-commerce","496":"ecommerce","2419":"eshopping","535":"nature","2422":"online-market","2420":"online-shopping","383":"online-store","497":"plant-store","495":"plants","2421":"purchases","2417":"reseller","733":"shop","2416":"shopping","749":"store","1024":"woocommerce"},"astra-sites-type":"free","astra-site-category":{"38":"ecommerce","39":"free"},"astra-sites-template-category":{"2769":"ecommerce","2857":"online-shopping"},"astra-site-page-builder":"gutenberg","categories":{"2500":"multipurpose"},"required-plugins":[{"slug":"astra-widgets","init":"astra-widgets\/astra-widgets.php","name":"Astra Widgets"},{"slug":"woocommerce","init":"woocommerce\/woocommerce.php","name":"WooCommerce"},{"slug":"woo-cart-abandonment-recovery","init":"woo-cart-abandonment-recovery\/woo-cart-abandonment-recovery.php","name":"WooCommerce Cart Abandonment Recovery"},{"slug":"ultimate-addons-for-gutenberg","init":"ultimate-addons-for-gutenberg\/ultimate-addons-for-gutenberg.php","name":"Spectra"},{"slug":"variation-swatches-woo","init":"variation-swatches-woo\/variation-swatches-woo.php","name":"Variation Swatches for WooCommerce"},{"slug":"sureforms","init":"sureforms\/sureforms.php","name":"SureForms"},{"slug":"woocommerce-payments","init":"woocommerce-payments\/woocommerce-payments.php","name":"WooPayments"}],"post-status":"publish","post-content":"","post-excerpt":"","pages":{"id-68346":{"title":"Store","featured-image-url":"https:\/\/websitedemos.net\/wp-content\/uploads\/2020\/10\/plant-store-08-store.jpg","thumbnail-image-url":"https:\/\/websitedemos.net\/wp-content\/uploads\/2020\/10\/plant-store-08-store-600x1973.jpg","astra-page-api-url":"https:\/\/websitedemos.net\/plant-store-08\/wp-json\/wp\/v2\/pages\/118","dynamic-page":"no","astra-page-url":"\/\/websitedemos.net\/plant-store-08\/store\/","astra-sites-tag":[],"site-pages-type":"free","site-pages-page-builder":"gutenberg","site-pages-category":[],"site-pages-parent-category":{"64":"ecommerce","61":"free"},"required-plugins":[{"slug":"astra-widgets","init":"astra-widgets\/astra-widgets.php","name":"Astra Widgets"},{"slug":"ultimate-addons-for-gutenberg","init":"ultimate-addons-for-gutenberg\/ultimate-addons-for-gutenberg.php","name":"Spectra"}],"spectra-ver":[]},"id-48432":{"title":"About Us","featured-image-url":"https:\/\/websitedemos.net\/wp-content\/uploads\/2020\/10\/plant-store-08-about-us.jpg","thumbnail-image-url":"https:\/\/websitedemos.net\/wp-content\/uploads\/2020\/10\/plant-store-08-about-us-600x1926.jpg","astra-page-api-url":"https:\/\/websitedemos.net\/plant-store-08\/wp-json\/wp\/v2\/pages\/119","dynamic-page":"no","astra-page-url":"\/\/websitedemos.net\/plant-store-08\/about-us\/","astra-sites-tag":{"352":"about"},"site-pages-type":"free","site-pages-page-builder":"gutenberg","site-pages-category":[],"site-pages-parent-category":{"64":"ecommerce","61":"free"},"required-plugins":[{"slug":"astra-widgets","init":"astra-widgets\/astra-widgets.php","name":"Astra Widgets"},{"slug":"ultimate-addons-for-gutenberg","init":"ultimate-addons-for-gutenberg\/ultimate-addons-for-gutenberg.php","name":"Spectra"}],"spectra-ver":[]},"id-48433":{"title":"Contact Us","featured-image-url":"https:\/\/websitedemos.net\/wp-content\/uploads\/2020\/10\/plant-store-08-contact-us.jpg","thumbnail-image-url":"https:\/\/websitedemos.net\/wp-content\/uploads\/2020\/10\/plant-store-08-contact-us-600x886.jpg","astra-page-api-url":"https:\/\/websitedemos.net\/plant-store-08\/wp-json\/wp\/v2\/pages\/120","dynamic-page":"no","astra-page-url":"\/\/websitedemos.net\/plant-store-08\/contact-us\/","astra-sites-tag":{"415":"contact"},"site-pages-type":"free","site-pages-page-builder":"gutenberg","site-pages-category":[],"site-pages-parent-category":{"64":"ecommerce","61":"free"},"required-plugins":[{"slug":"astra-widgets","init":"astra-widgets\/astra-widgets.php","name":"Astra Widgets"},{"slug":"ultimate-addons-for-gutenberg","init":"ultimate-addons-for-gutenberg\/ultimate-addons-for-gutenberg.php","name":"Spectra"},{"slug":"sureforms","init":"sureforms\/sureforms.php","name":"SureForms"}],"spectra-ver":[]},"id-48434":{"title":"Home","featured-image-url":"https:\/\/websitedemos.net\/wp-content\/uploads\/2020\/10\/plant-store-08.jpg","thumbnail-image-url":"https:\/\/websitedemos.net\/wp-content\/uploads\/2020\/10\/plant-store-08-600x2263.jpg","astra-page-api-url":"https:\/\/websitedemos.net\/plant-store-08\/wp-json\/wp\/v2\/pages\/15","dynamic-page":"yes","astra-page-url":"\/\/websitedemos.net\/plant-store-08\/","astra-sites-tag":{"814":"homepage"},"site-pages-type":"free","site-pages-page-builder":"gutenberg","site-pages-category":[],"site-pages-parent-category":{"64":"ecommerce","61":"free"},"required-plugins":[{"slug":"astra-widgets","init":"astra-widgets\/astra-widgets.php","name":"Astra Widgets"},{"slug":"ultimate-addons-for-gutenberg","init":"ultimate-addons-for-gutenberg\/ultimate-addons-for-gutenberg.php","name":"Spectra"},{"slug":"variation-swatches-woo","init":"variation-swatches-woo\/variation-swatches-woo.php","name":"Variation Swatches for WooCommerce"},{"slug":"woocommerce","init":"woocommerce\/woocommerce.php","name":"WooCommerce"},{"slug":"woo-cart-abandonment-recovery","init":"woo-cart-abandonment-recovery\/woo-cart-abandonment-recovery.php","name":"WooCommerce Cart Abandonment Recovery"},{"slug":"woocommerce-payments","init":"woocommerce-payments\/woocommerce-payments.php","name":"WooPayments"}],"spectra-ver":[]}},"spectra-ver":[],"query_args":{"post_type":"astra-sites","post_status":["publish"],"fields":"ids","no_found_rows":true,"paged":29,"posts_per_page":15,"tax_query":{"relation":"AND","0":{"relation":"OR","0":{"taxonomy":"spectra-blocks-ver","field":"slug","terms":["v2","v3"],"operator":"IN"},"1":{"taxonomy":"spectra-blocks-ver","operator":"NOT EXISTS"}},"1":{"taxonomy":"astra-sites-type","field":"slug","terms":["siteground"],"operator":"NOT IN"}},"orderby":"menu_order","order":"ASC"},"related-bb-template":"","related-elementor-template":"","related-gutenberg-template":"","related_ecommerce_template":75439,"ecommerce_parent_template":75439},"id-58999":{"title":"Wedding Invitation","id":58999,"publish-date":1643645131,"featured-image-url":"https:\/\/websitedemos.net\/wp-content\/uploads\/2022\/01\/wedding-invitation-02-home.jpg","thumbnail-image-url":"https:\/\/websitedemos.net\/wp-content\/uploads\/2022\/01\/wedding-invitation-02-home.jpg","fullpage-thumbnail-image-url":"https:\/\/websitedemos.net\/wp-content\/uploads\/2022\/01\/wedding-invitation-02-home.jpg","astra-site-url":"\/\/websitedemos.net\/wedding-invitation-02","astra-site-parent-id":2559,"astra-sites-tag":{"3416":"elementor","699":"invitation","2560":"reception-invitation","697":"wedding","1457":"wedding-invitation"},"astra-sites-type":"free","astra-site-category":{"27":"business","39":"free"},"astra-sites-template-category":{"2771":"one-page","2792":"wedding"},"astra-site-page-builder":"elementor","categories":{"3427":"default","2489":"event-invitation","3428":"free","2927":"one-page"},"required-plugins":[{"slug":"elementor","init":"elementor\/elementor.php","name":"Elementor"},{"slug":"sureforms","init":"sureforms\/sureforms.php","name":"SureForms"}],"post-status":"publish","post-content":"<!-- wp:paragraph -->\n<p>The Wedding Invitation template is a simple, yet elegant one page website template designed specifically to deliver wedding invitations for the 21<sup>st<\/sup> century.<\/p>\n<!-- \/wp:paragraph -->\n\n<!-- wp:paragraph -->\n<p>The template begins with a full size image of the bride and groom and opens out into a light and easygoing page with parallax effect. It can outline the what, where and when and be customized to include any extra content you need, including an RSVP form.<\/p>\n<!-- \/wp:paragraph -->\n\n<!-- wp:heading -->\n<h2>Key features of the Wedding Invitation template<\/h2>\n<!-- \/wp:heading -->\n\n<!-- wp:list -->\n<ul><li>Elegant single page wedding invitation template<\/li><li>Uses elegant colors and fonts<\/li><li>Smooth parallax effects throughout the page<\/li><li>Flexible content areas so you can design the page however you like<\/li><li>Includes RSVP form for total convenience<\/li><li>Full compatibility with leading page builders<\/li><\/ul>\n<!-- \/wp:list -->","post-excerpt":"Elegant wedding invitation template with a romantic feel and essential features","pages":{"id-59000":{"title":"Home","featured-image-url":"https:\/\/websitedemos.net\/wp-content\/uploads\/2022\/01\/wedding-invitation-02-home.jpg","thumbnail-image-url":"https:\/\/websitedemos.net\/wp-content\/uploads\/2022\/01\/wedding-invitation-02-home.jpg","astra-page-api-url":"https:\/\/websitedemos.net\/wedding-invitation-02\/wp-json\/wp\/v2\/pages\/6","dynamic-page":"no","astra-page-url":"\/\/websitedemos.net\/wedding-invitation-02\/","astra-sites-tag":{"423":"home"},"site-pages-type":"free","site-pages-page-builder":"elementor","site-pages-category":[],"site-pages-parent-category":{"60":"business","61":"free"},"required-plugins":[{"slug":"elementor","init":"elementor\/elementor.php","name":"Elementor"},{"slug":"sureforms","init":"sureforms\/sureforms.php","name":"SureForms"}],"spectra-ver":[]}},"spectra-ver":[],"query_args":{"post_type":"astra-sites","post_status":["publish"],"fields":"ids","no_found_rows":true,"paged":29,"posts_per_page":15,"tax_query":{"relation":"AND","0":{"relation":"OR","0":{"taxonomy":"spectra-blocks-ver","field":"slug","terms":["v2","v3"],"operator":"IN"},"1":{"taxonomy":"spectra-blocks-ver","operator":"NOT EXISTS"}},"1":{"taxonomy":"astra-sites-type","field":"slug","terms":["siteground"],"operator":"NOT IN"}},"orderby":"menu_order","order":"ASC"},"related-bb-template":"","related-elementor-template":"","related-gutenberg-template":71180,"related_ecommerce_template":0,"ecommerce_parent_template":""},"id-75439":{"title":"Simply Natural","id":75439,"publish-date":1691769102,"featured-image-url":"https:\/\/websitedemos.net\/wp-content\/uploads\/2023\/08\/plants-stores-08.jpg","thumbnail-image-url":"https:\/\/websitedemos.net\/wp-content\/uploads\/2023\/08\/plants-stores-08-600x2204.jpg","fullpage-thumbnail-image-url":"https:\/\/websitedemos.net\/wp-content\/uploads\/2023\/08\/plants-stores-08-400x1469.jpg","astra-site-url":"\/\/websitedemos.net\/plants-stores-08","astra-site-parent-id":3372,"astra-sites-tag":{"2419":"eshopping","2422":"online-market","2390":"online-plant-shop","2420":"online-shopping","383":"online-store","1414":"plant-shop","497":"plant-store","495":"plants","2421":"purchases","2417":"reseller","733":"shop","2416":"shopping","749":"store","3550":"surecart"},"astra-sites-type":"free","astra-site-category":{"38":"ecommerce","39":"free"},"astra-sites-template-category":{"2769":"ecommerce","2857":"online-shopping"},"astra-site-page-builder":"gutenberg","categories":{"3427":"default","2495":"ecommerce","3428":"free","2476":"gardening"},"required-plugins":[{"slug":"ultimate-addons-for-gutenberg","init":"ultimate-addons-for-gutenberg\/ultimate-addons-for-gutenberg.php","name":"Spectra"},{"slug":"surecart","init":"surecart\/surecart.php","name":"SureCart"}],"post-status":"publish","post-content":"","post-excerpt":"","pages":{"id-164017":{"title":"Contact Us","featured-image-url":"https:\/\/websitedemos.net\/wp-content\/uploads\/2026\/02\/plants-stores-09-contact.jpg","thumbnail-image-url":"https:\/\/websitedemos.net\/wp-content\/uploads\/2026\/02\/plants-stores-09-contact-600x921.jpg","astra-page-api-url":"https:\/\/websitedemos.net\/plants-stores-09\/wp-json\/wp\/v2\/pages\/612","dynamic-page":"no","astra-page-url":"\/\/websitedemos.net\/plants-stores-09\/contact-us\/","astra-sites-tag":{"415":"contact"},"site-pages-type":"free","site-pages-page-builder":"gutenberg","site-pages-category":[],"site-pages-parent-category":{"64":"ecommerce","61":"free"},"required-plugins":[{"slug":"ultimate-addons-for-gutenberg","init":"ultimate-addons-for-gutenberg\/ultimate-addons-for-gutenberg.php","name":"Spectra"},{"slug":"sureforms","init":"sureforms\/sureforms.php","name":"SureForms"}],"spectra-ver":"v3"},"id-164016":{"title":"About Us","featured-image-url":"https:\/\/websitedemos.net\/wp-content\/uploads\/2026\/02\/plants-stores-09-about.jpg","thumbnail-image-url":"https:\/\/websitedemos.net\/wp-content\/uploads\/2026\/02\/plants-stores-09-about-600x1956.jpg","astra-page-api-url":"https:\/\/websitedemos.net\/plants-stores-09\/wp-json\/wp\/v2\/pages\/611","dynamic-page":"no","astra-page-url":"\/\/websitedemos.net\/plants-stores-09\/about-us\/","astra-sites-tag":{"352":"about"},"site-pages-type":"free","site-pages-page-builder":"gutenberg","site-pages-category":[],"site-pages-parent-category":{"64":"ecommerce","61":"free"},"required-plugins":[{"slug":"ultimate-addons-for-gutenberg","init":"ultimate-addons-for-gutenberg\/ultimate-addons-for-gutenberg.php","name":"Spectra"}],"spectra-ver":"v3"},"id-164018":{"title":"Home","featured-image-url":"https:\/\/websitedemos.net\/wp-content\/uploads\/2026\/02\/plants-stores-09.jpg","thumbnail-image-url":"https:\/\/websitedemos.net\/wp-content\/uploads\/2026\/02\/plants-stores-09-600x2204.jpg","astra-page-api-url":"https:\/\/websitedemos.net\/plants-stores-09\/wp-json\/wp\/v2\/pages\/605","dynamic-page":"yes","astra-page-url":"\/\/websitedemos.net\/plants-stores-09\/","astra-sites-tag":{"423":"home"},"site-pages-type":"free","site-pages-page-builder":"gutenberg","site-pages-category":[],"site-pages-parent-category":{"64":"ecommerce","61":"free"},"required-plugins":[{"slug":"ultimate-addons-for-gutenberg","init":"ultimate-addons-for-gutenberg\/ultimate-addons-for-gutenberg.php","name":"Spectra"},{"slug":"surecart","init":"surecart\/surecart.php","name":"SureCart"}],"spectra-ver":"v3"},"id-75442":{"title":"Home","featured-image-url":"https:\/\/websitedemos.net\/wp-content\/uploads\/2023\/08\/plants-stores-08.jpg","thumbnail-image-url":"https:\/\/websitedemos.net\/wp-content\/uploads\/2023\/08\/plants-stores-08-600x2204.jpg","astra-page-api-url":"https:\/\/websitedemos.net\/plants-stores-08\/wp-json\/wp\/v2\/pages\/605","dynamic-page":"yes","astra-page-url":"\/\/websitedemos.net\/plants-stores-08\/","astra-sites-tag":{"423":"home"},"site-pages-type":"free","site-pages-page-builder":"gutenberg","site-pages-category":[],"site-pages-parent-category":{"64":"ecommerce","61":"free"},"required-plugins":[{"slug":"ultimate-addons-for-gutenberg","init":"ultimate-addons-for-gutenberg\/ultimate-addons-for-gutenberg.php","name":"Spectra"},{"slug":"surecart","init":"surecart\/surecart.php","name":"SureCart"}],"spectra-ver":[]},"id-75440":{"title":"About Us","featured-image-url":"https:\/\/websitedemos.net\/wp-content\/uploads\/2023\/08\/plants-stores-08-about.jpg","thumbnail-image-url":"https:\/\/websitedemos.net\/wp-content\/uploads\/2023\/08\/plants-stores-08-about-600x1956.jpg","astra-page-api-url":"https:\/\/websitedemos.net\/plants-stores-08\/wp-json\/wp\/v2\/pages\/611","dynamic-page":"no","astra-page-url":"\/\/websitedemos.net\/plants-stores-08\/about-us\/","astra-sites-tag":{"352":"about"},"site-pages-type":"free","site-pages-page-builder":"gutenberg","site-pages-category":[],"site-pages-parent-category":{"64":"ecommerce","61":"free"},"required-plugins":[{"slug":"ultimate-addons-for-gutenberg","init":"ultimate-addons-for-gutenberg\/ultimate-addons-for-gutenberg.php","name":"Spectra"}],"spectra-ver":[]},"id-75499":{"title":"Shop","featured-image-url":"","thumbnail-image-url":"","astra-page-api-url":"https:\/\/websitedemos.net\/plants-stores-08\/wp-json\/wp\/v2\/pages\/285","dynamic-page":"no","astra-page-url":"\/\/websitedemos.net\/plants-stores-08\/shop\/","astra-sites-tag":[],"site-pages-type":"free","site-pages-page-builder":"gutenberg","site-pages-category":[],"site-pages-parent-category":{"64":"ecommerce","61":"free"},"required-plugins":[{"slug":"surecart","init":"surecart\/surecart.php","name":"SureCart"}],"spectra-ver":[]},"id-75497":{"title":"Checkout","featured-image-url":"","thumbnail-image-url":"","astra-page-api-url":"https:\/\/websitedemos.net\/plants-stores-08\/wp-json\/wp\/v2\/pages\/282","dynamic-page":"no","astra-page-url":"\/\/websitedemos.net\/plants-stores-08\/checkout\/","astra-sites-tag":[],"site-pages-type":"free","site-pages-page-builder":"gutenberg","site-pages-category":[],"site-pages-parent-category":{"64":"ecommerce","61":"free"},"required-plugins":[{"slug":"surecart","init":"surecart\/surecart.php","name":"SureCart"}],"spectra-ver":[]},"id-75498":{"title":"Dashboard","featured-image-url":"","thumbnail-image-url":"","astra-page-api-url":"https:\/\/websitedemos.net\/plants-stores-08\/wp-json\/wp\/v2\/pages\/283","dynamic-page":"no","astra-page-url":"\/\/websitedemos.net\/plants-stores-08\/customer-dashboard\/","astra-sites-tag":[],"site-pages-type":"free","site-pages-page-builder":"gutenberg","site-pages-category":[],"site-pages-parent-category":{"64":"ecommerce","61":"free"},"required-plugins":[{"slug":"surecart","init":"surecart\/surecart.php","name":"SureCart"}],"spectra-ver":[]},"id-75441":{"title":"Contact Us","featured-image-url":"https:\/\/websitedemos.net\/wp-content\/uploads\/2023\/08\/plants-stores-08-contact.jpg","thumbnail-image-url":"https:\/\/websitedemos.net\/wp-content\/uploads\/2023\/08\/plants-stores-08-contact-600x921.jpg","astra-page-api-url":"https:\/\/websitedemos.net\/plants-stores-08\/wp-json\/wp\/v2\/pages\/612","dynamic-page":"no","astra-page-url":"\/\/websitedemos.net\/plants-stores-08\/contact-us\/","astra-sites-tag":{"415":"contact"},"site-pages-type":"free","site-pages-page-builder":"gutenberg","site-pages-category":[],"site-pages-parent-category":{"64":"ecommerce","61":"free"},"required-plugins":[{"slug":"ultimate-addons-for-gutenberg","init":"ultimate-addons-for-gutenberg\/ultimate-addons-for-gutenberg.php","name":"Spectra"}],"spectra-ver":[]}},"spectra-ver":[],"query_args":{"post_type":"astra-sites","post_status":["publish"],"fields":"ids","no_found_rows":true,"paged":29,"posts_per_page":15,"tax_query":{"relation":"AND","0":{"relation":"OR","0":{"taxonomy":"spectra-blocks-ver","field":"slug","terms":["v2","v3"],"operator":"IN"},"1":{"taxonomy":"spectra-blocks-ver","operator":"NOT EXISTS"}},"1":{"taxonomy":"astra-sites-type","field":"slug","terms":["siteground"],"operator":"NOT IN"}},"orderby":"menu_order","order":"ASC"},"related-bb-template":"","related-elementor-template":"","related-gutenberg-template":"","related_ecommerce_template":48431,"ecommerce_parent_template":""},"id-49236":{"title":"Yoga Studio","id":49236,"publish-date":1608714979,"featured-image-url":"https:\/\/websitedemos.net\/wp-content\/uploads\/2020\/12\/yoga-studio-04-home.jpg","thumbnail-image-url":"https:\/\/websitedemos.net\/wp-content\/uploads\/2020\/12\/yoga-studio-04-home.jpg","fullpage-thumbnail-image-url":"https:\/\/websitedemos.net\/wp-content\/uploads\/2020\/12\/yoga-studio-04-home.jpg","astra-site-url":"\/\/websitedemos.net\/yoga-studio-04","astra-site-parent-id":1787,"astra-sites-tag":{"3416":"elementor","499":"fitness","976":"gym-instructor","1844":"premium","395":"yoga-instructor","397":"yoga-studio","398":"yoga-trainer"},"astra-sites-type":"agency-mini","astra-site-category":{"27":"business"},"astra-sites-template-category":{"2777":"business","2825":"coaching","2787":"gym-fitness","2808":"yoga"},"astra-site-page-builder":"elementor","categories":{"3427":"default","2480":"fitness-wellness","3429":"premium"},"required-plugins":[{"slug":"elementor","init":"elementor\/elementor.php","name":"Elementor"},{"slug":"wpforms-lite","init":"wpforms-lite\/wpforms.php","name":"WPForms Lite"},{"slug":"latepoint","init":"latepoint\/latepoint.php","name":"LatePoint"}],"post-status":"publish","post-content":"<!-- wp:paragraph -->\n<p>Whether you\u2019re an independent yoga instructor or a full-fledged yoga training institute, the Yoga Studio template is exactly what you want. The pastel colors and the impressive use of images make this template tailor-made for a yoga studio website.<\/p>\n<!-- \/wp:paragraph -->\n\n<!-- wp:paragraph -->\n<p>Include the various yoga poses, popular classes, instructor details, and customer reviews, among other things. You can also stay connected with your customers through a newsletter subscription form.<\/p>\n<!-- \/wp:paragraph -->\n\n<!-- wp:heading -->\n<h2>Key features of the Yoga Studio template<\/h2>\n<!-- \/wp:heading -->\n\n<!-- wp:list -->\n<ul><li>Elegant-looking website template, perfect for a yoga studio website<\/li><li>Pastel colors, typography, and images set the tone of the website<\/li><li>Impressive layout that allows you to promote your classes clutter-free<\/li><li>Include details of instructors and customer reviews, among other things<\/li><li>Full compatibility with leading page builders<\/li><\/ul>\n<!-- \/wp:list -->","post-excerpt":"An elegant-looking template that\u2019s tailor-made for building a yoga studio website","pages":{"id-47693":{"title":"Home","featured-image-url":"https:\/\/websitedemos.net\/wp-content\/uploads\/2020\/12\/yoga-studio-04-home.jpg","thumbnail-image-url":"https:\/\/websitedemos.net\/wp-content\/uploads\/2020\/12\/yoga-studio-04-home.jpg","astra-page-api-url":"https:\/\/websitedemos.net\/yoga-studio-04\/wp-json\/wp\/v2\/pages\/11","dynamic-page":"no","astra-page-url":"\/\/websitedemos.net\/yoga-studio-04\/","astra-sites-tag":{"423":"home"},"site-pages-type":"agency-mini","site-pages-page-builder":"elementor","site-pages-category":[],"site-pages-parent-category":{"60":"business"},"required-plugins":[{"slug":"elementor","init":"elementor\/elementor.php","name":"Elementor"},{"slug":"latepoint","init":"latepoint\/latepoint.php","name":"LatePoint"}],"spectra-ver":[]},"id-47690":{"title":"About Us","featured-image-url":"https:\/\/websitedemos.net\/wp-content\/uploads\/2020\/12\/yoga-studio-04-about.jpg","thumbnail-image-url":"https:\/\/websitedemos.net\/wp-content\/uploads\/2020\/12\/yoga-studio-04-about.jpg","astra-page-api-url":"https:\/\/websitedemos.net\/yoga-studio-04\/wp-json\/wp\/v2\/pages\/135","dynamic-page":"no","astra-page-url":"\/\/websitedemos.net\/yoga-studio-04\/about-us\/","astra-sites-tag":{"352":"about"},"site-pages-type":"agency-mini","site-pages-page-builder":"elementor","site-pages-category":[],"site-pages-parent-category":{"60":"business"},"required-plugins":[{"slug":"elementor","init":"elementor\/elementor.php","name":"Elementor"}],"spectra-ver":[]},"id-47691":{"title":"Classes","featured-image-url":"https:\/\/websitedemos.net\/wp-content\/uploads\/2020\/12\/yoga-studio-04-classes.jpg","thumbnail-image-url":"https:\/\/websitedemos.net\/wp-content\/uploads\/2020\/12\/yoga-studio-04-classes.jpg","astra-page-api-url":"https:\/\/websitedemos.net\/yoga-studio-04\/wp-json\/wp\/v2\/pages\/181","dynamic-page":"no","astra-page-url":"\/\/websitedemos.net\/yoga-studio-04\/classes\/","astra-sites-tag":{"557":"classes"},"site-pages-type":"agency-mini","site-pages-page-builder":"elementor","site-pages-category":[],"site-pages-parent-category":{"60":"business"},"required-plugins":[{"slug":"elementor","init":"elementor\/elementor.php","name":"Elementor"},{"slug":"latepoint","init":"latepoint\/latepoint.php","name":"LatePoint"}],"spectra-ver":[]},"id-47694":{"title":"Testimonials","featured-image-url":"https:\/\/websitedemos.net\/wp-content\/uploads\/2020\/12\/yoga-studio-04-testimonials.jpg","thumbnail-image-url":"https:\/\/websitedemos.net\/wp-content\/uploads\/2020\/12\/yoga-studio-04-testimonials.jpg","astra-page-api-url":"https:\/\/websitedemos.net\/yoga-studio-04\/wp-json\/wp\/v2\/pages\/226","dynamic-page":"no","astra-page-url":"\/\/websitedemos.net\/yoga-studio-04\/testimonials\/","astra-sites-tag":{"433":"testimonials"},"site-pages-type":"agency-mini","site-pages-page-builder":"elementor","site-pages-category":[],"site-pages-parent-category":{"60":"business"},"required-plugins":[{"slug":"elementor","init":"elementor\/elementor.php","name":"Elementor"}],"spectra-ver":[]},"id-47692":{"title":"Contact Us","featured-image-url":"https:\/\/websitedemos.net\/wp-content\/uploads\/2020\/12\/yoga-studio-04-contact.jpg","thumbnail-image-url":"https:\/\/websitedemos.net\/wp-content\/uploads\/2020\/12\/yoga-studio-04-contact.jpg","astra-page-api-url":"https:\/\/websitedemos.net\/yoga-studio-04\/wp-json\/wp\/v2\/pages\/269","dynamic-page":"no","astra-page-url":"\/\/websitedemos.net\/yoga-studio-04\/contact-us\/","astra-sites-tag":{"454":"contact-us"},"site-pages-type":"agency-mini","site-pages-page-builder":"elementor","site-pages-category":[],"site-pages-parent-category":{"60":"business"},"required-plugins":[{"slug":"elementor","init":"elementor\/elementor.php","name":"Elementor"},{"slug":"wpforms-lite","init":"wpforms-lite\/wpforms.php","name":"WPForms Lite"}],"spectra-ver":[]}},"spectra-ver":[],"query_args":{"post_type":"astra-sites","post_status":["publish"],"fields":"ids","no_found_rows":true,"paged":29,"posts_per_page":15,"tax_query":{"relation":"AND","0":{"relation":"OR","0":{"taxonomy":"spectra-blocks-ver","field":"slug","terms":["v2","v3"],"operator":"IN"},"1":{"taxonomy":"spectra-blocks-ver","operator":"NOT EXISTS"}},"1":{"taxonomy":"astra-sites-type","field":"slug","terms":["siteground"],"operator":"NOT IN"}},"orderby":"menu_order","order":"ASC"},"related-bb-template":"","related-elementor-template":22100,"related-gutenberg-template":86549,"related_ecommerce_template":0,"ecommerce_parent_template":""},"id-86304":{"title":"Transport Services","id":86304,"publish-date":1707499299,"featured-image-url":"https:\/\/websitedemos.net\/wp-content\/uploads\/2024\/02\/transport-services-07.jpg","thumbnail-image-url":"https:\/\/websitedemos.net\/wp-content\/uploads\/2024\/02\/transport-services-07-600x2842.jpg","fullpage-thumbnail-image-url":"https:\/\/websitedemos.net\/wp-content\/uploads\/2024\/02\/transport-services-07-400x1895.jpg","astra-site-url":"\/\/websitedemos.net\/transport-services-07","astra-site-parent-id":3486,"astra-sites-tag":{"394":"air-cargo","845":"blue","391":"cargo-services","392":"freight-services","388":"good-carrier","389":"logistics","399":"one-page","846":"red","393":"road-transport","390":"shipping","366":"transport","387":"trucking"},"astra-sites-type":"agency-mini","astra-site-category":{"27":"business"},"astra-sites-template-category":{"2777":"business","2771":"one-page","2831":"service","2806":"transportation"},"astra-site-page-builder":"gutenberg","categories":{"3430":"dark","2927":"one-page","2473":"transport"},"required-plugins":[{"slug":"ultimate-addons-for-gutenberg","init":"ultimate-addons-for-gutenberg\/ultimate-addons-for-gutenberg.php","name":"Spectra"},{"slug":"sureforms","init":"sureforms\/sureforms.php","name":"SureForms"}],"post-status":"publish","post-content":"","post-excerpt":"","pages":{"id-86305":{"title":"One Page Website","featured-image-url":"https:\/\/websitedemos.net\/wp-content\/uploads\/2024\/02\/transport-services-07.jpg","thumbnail-image-url":"https:\/\/websitedemos.net\/wp-content\/uploads\/2024\/02\/transport-services-07-600x2842.jpg","astra-page-api-url":"https:\/\/websitedemos.net\/transport-services-07\/wp-json\/wp\/v2\/pages\/297","dynamic-page":"no","astra-page-url":"\/\/websitedemos.net\/transport-services-07\/","astra-sites-tag":{"850":"landing-page"},"site-pages-type":"agency-mini","site-pages-page-builder":"gutenberg","site-pages-category":[],"site-pages-parent-category":{"60":"business"},"required-plugins":[{"slug":"ultimate-addons-for-gutenberg","init":"ultimate-addons-for-gutenberg\/ultimate-addons-for-gutenberg.php","name":"Spectra"},{"slug":"sureforms","init":"sureforms\/sureforms.php","name":"SureForms"}],"spectra-ver":"v3"}},"spectra-ver":[],"query_args":{"post_type":"astra-sites","post_status":["publish"],"fields":"ids","no_found_rows":true,"paged":29,"posts_per_page":15,"tax_query":{"relation":"AND","0":{"relation":"OR","0":{"taxonomy":"spectra-blocks-ver","field":"slug","terms":["v2","v3"],"operator":"IN"},"1":{"taxonomy":"spectra-blocks-ver","operator":"NOT EXISTS"}},"1":{"taxonomy":"astra-sites-type","field":"slug","terms":["siteground"],"operator":"NOT IN"}},"orderby":"menu_order","order":"ASC"},"related-bb-template":"","related-elementor-template":"","related-gutenberg-template":"","related_ecommerce_template":0,"ecommerce_parent_template":""},"id-58951":{"title":"Limousine Rental Agency","id":58951,"publish-date":1643644485,"featured-image-url":"https:\/\/websitedemos.net\/wp-content\/uploads\/2021\/10\/rental-agency-02-homepage.jpg","thumbnail-image-url":"https:\/\/websitedemos.net\/wp-content\/uploads\/2021\/10\/rental-agency-02-homepage.jpg","fullpage-thumbnail-image-url":"https:\/\/websitedemos.net\/wp-content\/uploads\/2021\/10\/rental-agency-02-homepage.jpg","astra-site-url":"\/\/websitedemos.net\/rental-agency-02","astra-site-parent-id":2536,"astra-sites-tag":{"3416":"elementor","2540":"limousine","2538":"rent-limousines","2539":"rent-services","2537":"rental-agency","2541":"sedan"},"astra-sites-type":"free","astra-site-category":{"27":"business","39":"free"},"astra-sites-template-category":{"2832":"property"},"astra-site-page-builder":"elementor","categories":{"2475":"automotive","3427":"default","3428":"free","2473":"transport"},"required-plugins":[{"slug":"elementor","init":"elementor\/elementor.php","name":"Elementor"},{"slug":"header-footer-elementor","init":"header-footer-elementor\/header-footer-elementor.php","name":"Ultimate Addons for Elementor Lite"},{"slug":"sureforms","init":"sureforms\/sureforms.php","name":"SureForms"}],"post-status":"publish","post-content":"<!-- wp:paragraph -->\n<p>The Limousine Rental Agency template opens with a full screen image with complementing colors that create a feeling of luxury ideal for this niche.<\/p>\n<!-- \/wp:paragraph -->\n\n<!-- wp:paragraph -->\n<p>The rest of the design continues the look with alternating dark and light backgrounds, an attractive parallax effect and lots of content areas. Each page reflects the same values to create a very attractive website.<\/p>\n<!-- \/wp:paragraph -->\n\n<!-- wp:heading {\"UAGDay\":[]} -->\n<h2 class=\"wp-block-heading\">Key features of the Limousine Rental Agency template<\/h2>\n<!-- \/wp:heading -->\n\n<!-- wp:list -->\n<ul><!-- wp:list-item -->\n<li>Homepage and extra pages all use luxurious colors and design<\/li>\n<!-- \/wp:list-item -->\n\n<!-- wp:list-item -->\n<li>Parallax effect on the homepage<\/li>\n<!-- \/wp:list-item -->\n\n<!-- wp:list-item -->\n<li>Good use of white space to add modernity<\/li>\n<!-- \/wp:list-item -->\n\n<!-- wp:list-item -->\n<li>Template includes all essential pages including map and contact<\/li>\n<!-- \/wp:list-item -->\n\n<!-- wp:list-item -->\n<li>Lots of content areas to add extra features or services<\/li>\n<!-- \/wp:list-item -->\n\n<!-- wp:list-item -->\n<li>Fully compatible with leading page builders<\/li>\n<!-- \/wp:list-item --><\/ul>\n<!-- \/wp:list -->","post-excerpt":"Professional template with nice layout and modern design ideal for limousine rentals","pages":{"id-58462":{"title":"Home","featured-image-url":"https:\/\/websitedemos.net\/wp-content\/uploads\/2021\/10\/rental-agency-02-homepage.jpg","thumbnail-image-url":"https:\/\/websitedemos.net\/wp-content\/uploads\/2021\/10\/rental-agency-02-homepage.jpg","astra-page-api-url":"https:\/\/websitedemos.net\/rental-agency-02\/wp-json\/wp\/v2\/pages\/6","dynamic-page":"no","astra-page-url":"\/\/websitedemos.net\/rental-agency-02\/","astra-sites-tag":{"423":"home"},"site-pages-type":"free","site-pages-page-builder":"elementor","site-pages-category":[],"site-pages-parent-category":{"60":"business","61":"free"},"required-plugins":[{"slug":"elementor","init":"elementor\/elementor.php","name":"Elementor"}],"spectra-ver":[]},"id-58460":{"title":"About Us","featured-image-url":"https:\/\/websitedemos.net\/wp-content\/uploads\/2021\/10\/rental-agency-02-about-us.jpg","thumbnail-image-url":"https:\/\/websitedemos.net\/wp-content\/uploads\/2021\/10\/rental-agency-02-about-us.jpg","astra-page-api-url":"https:\/\/websitedemos.net\/rental-agency-02\/wp-json\/wp\/v2\/pages\/9","dynamic-page":"no","astra-page-url":"\/\/websitedemos.net\/rental-agency-02\/about-us\/","astra-sites-tag":{"352":"about"},"site-pages-type":"free","site-pages-page-builder":"elementor","site-pages-category":[],"site-pages-parent-category":{"60":"business","61":"free"},"required-plugins":[{"slug":"elementor","init":"elementor\/elementor.php","name":"Elementor"}],"spectra-ver":[]},"id-58464":{"title":"Services","featured-image-url":"https:\/\/websitedemos.net\/wp-content\/uploads\/2021\/10\/rental-agency-02-services.jpg","thumbnail-image-url":"https:\/\/websitedemos.net\/wp-content\/uploads\/2021\/10\/rental-agency-02-services.jpg","astra-page-api-url":"https:\/\/websitedemos.net\/rental-agency-02\/wp-json\/wp\/v2\/pages\/11","dynamic-page":"no","astra-page-url":"\/\/websitedemos.net\/rental-agency-02\/services\/","astra-sites-tag":{"425":"services"},"site-pages-type":"free","site-pages-page-builder":"elementor","site-pages-category":[],"site-pages-parent-category":{"60":"business","61":"free"},"required-plugins":[{"slug":"elementor","init":"elementor\/elementor.php","name":"Elementor"},{"slug":"header-footer-elementor","init":"header-footer-elementor\/header-footer-elementor.php","name":"Ultimate Addons for Elementor Lite"}],"spectra-ver":[]},"id-58463":{"title":"Our Fleet","featured-image-url":"https:\/\/websitedemos.net\/wp-content\/uploads\/2021\/10\/rental-agency-02-our-fleet.jpg","thumbnail-image-url":"https:\/\/websitedemos.net\/wp-content\/uploads\/2021\/10\/rental-agency-02-our-fleet.jpg","astra-page-api-url":"https:\/\/websitedemos.net\/rental-agency-02\/wp-json\/wp\/v2\/pages\/13","dynamic-page":"no","astra-page-url":"\/\/websitedemos.net\/rental-agency-02\/our-fleet\/","astra-sites-tag":{"2445":"fleet"},"site-pages-type":"free","site-pages-page-builder":"elementor","site-pages-category":[],"site-pages-parent-category":{"60":"business","61":"free"},"required-plugins":[{"slug":"elementor","init":"elementor\/elementor.php","name":"Elementor"}],"spectra-ver":[]},"id-58461":{"title":"Contact","featured-image-url":"https:\/\/websitedemos.net\/wp-content\/uploads\/2021\/10\/rental-agency-02-contact.jpg","thumbnail-image-url":"https:\/\/websitedemos.net\/wp-content\/uploads\/2021\/10\/rental-agency-02-contact.jpg","astra-page-api-url":"https:\/\/websitedemos.net\/rental-agency-02\/wp-json\/wp\/v2\/pages\/15","dynamic-page":"no","astra-page-url":"\/\/websitedemos.net\/rental-agency-02\/contact\/","astra-sites-tag":{"415":"contact"},"site-pages-type":"free","site-pages-page-builder":"elementor","site-pages-category":[],"site-pages-parent-category":{"60":"business","61":"free"},"required-plugins":[{"slug":"elementor","init":"elementor\/elementor.php","name":"Elementor"},{"slug":"sureforms","init":"sureforms\/sureforms.php","name":"SureForms"}],"spectra-ver":[]}},"spectra-ver":[],"query_args":{"post_type":"astra-sites","post_status":["publish"],"fields":"ids","no_found_rows":true,"paged":29,"posts_per_page":15,"tax_query":{"relation":"AND","0":{"relation":"OR","0":{"taxonomy":"spectra-blocks-ver","field":"slug","terms":["v2","v3"],"operator":"IN"},"1":{"taxonomy":"spectra-blocks-ver","operator":"NOT EXISTS"}},"1":{"taxonomy":"astra-sites-type","field":"slug","terms":["siteground"],"operator":"NOT IN"}},"orderby":"menu_order","order":"ASC"},"related-bb-template":"","related-elementor-template":58951,"related-gutenberg-template":59202,"related_ecommerce_template":0,"ecommerce_parent_template":""}}